Workbook

Sheet How to use
B2: MyFinMantra — Budget & Forecast
B3: Client service format · Clear books. Confident business.
B5: Purpose | C5: Annual budget built from a few assumptions, monthly budget vs actual with favourable / adverse flags, and a rolling forecast that blends actuals for closed months with budget for the rest of the year.
B7: Colour legend
B8: 12,500 | C8: Blue text on yellow = input. Type or paste your client's figures here.
B9: Formula | C9: Black text = formula. Don't overwrite; it updates automatically.
B10: Header | C10: Section and column headings.
B12: Steps
B13: Step 1 | C13: On 'Assumptions', set the client name and the drivers: starting revenue, growth, cost ratios, headcount and fixed costs.
B14: Step 2 | C14: Review 'Budget' — every month calculates from the assumptions. Adjust headcount by month in the blue row.
B15: Step 3 | C15: Each month, enter actual figures on 'Actuals' (from Tally / Zoho).
B16: Step 4 | C16: On 'Budget vs Actual', pick the month to review. Variances are flagged Favourable or Adverse, for the month and year to date.
B17: Step 5 | C17: On 'Rolling Forecast', set the last closed month. The full-year estimate updates automatically: actuals to date + budget for the remaining months.
B19: Notes
C20: Favourable means higher than budget for income and profit lines, and lower than budget for cost lines.
C21: Employee cost = headcount × average monthly cost per employee, with the annual increment applied from the increment month onwards.
B23: Sample figures are filled in so you can see how the format works. Replace them with your own data.
B25: Free template by MyFinMantra
B26: Accounting, GST, payroll and Virtual CFO services · www.myfinmantra.com · WhatsApp +91 97118 99555
B27: General template for guidance only — verify rates and rules for your case. Not professional advice.

Sheet Assumptions
B2: Budget assumptions
B3: Change the blue cells; the whole budget updates
B5: Client name | C5: Sample Traders Pvt Ltd
B6: Financial year | C6: 2026-27
B8: Revenue — first month (April) (₹) | C8: 1900000 | D8: From last year's March run-rate
B9: Revenue growth per month | C9: 0.03 | D9: Compound monthly growth
B10: Other income per month (₹) | C10: 20000 | D10: Interest, misc. receipts
B11: Direct costs as % of revenue | C11: 0.4 | D11: From last year's gross margin
B12: Average monthly cost per employee (₹) | C12: 30000 | D12: CTC ÷ 12, incl. PF/ESI
B13: Annual increment | C13: 0.08 | D13: Applied from the increment month
B14: Increment effective from (month) | C14: Oct-26 | D14: Pick from dropdown
B15: Rent & utilities per month (₹) | C15: 85000 | D15: Per lease agreement
B16: Professional & consultancy fees per month (₹) | C16: 45000
B17: Sales & marketing as % of revenue | C17: 0.03
B18: Admin & other expenses per month (₹) | C18: 55000
B19: Depreciation per month (₹) | C19: 30000 | D19: From fixed asset register
B20: Finance costs per month (₹) | C20: 17000 | D20: Loan interest
B21: Tax rate on profit | C21: 0.25 | D21: Effective rate incl. surcharge & cess
B23: Last closed month (actuals available up to) | C23: Sep-26 | D23: Drives 'Rolling Forecast'

Sheet Budget
B2: Annual budget — monthly
B3: Calculated from 'Assumptions'. Only the headcount row is an input.
B5: Particulars (₹) | C5: Apr-26 | D5: May-26 | E5: Jun-26 | F5: Jul-26 | G5: Aug-26 | H5: Sep-26 | I5: Oct-26 | J5: Nov-26 | K5: Dec-26 | L5: Jan-27 | M5: Feb-27 | N5: Mar-27 | O5: Full year
B6: Revenue from operations | C6: =Assumptions!$C$8 -> 1900000 | D6: =C6*(1+Assumptions!$C$9) -> 1957000 | E6: =D6*(1+Assumptions!$C$9) -> 2015710 | F6: =E6*(1+Assumptions!$C$9) -> 2076181.3 | G6: =F6*(1+Assumptions!$C$9) -> 2138466.7 | H6: =G6*(1+Assumptions!$C$9) -> 2202620.7 | I6: =H6*(1+Assumptions!$C$9) -> 2268699.4 | J6: =I6*(1+Assumptions!$C$9) -> 2336760.3 | K6: =J6*(1+Assumptions!$C$9) -> 2406863.2 | ... N6: =M6*(1+Assumptions!$C$9) -> 2630044.4 | O6: =SUM(C6:N6) -> 26964856
B7: Other income | C7: =Assumptions!$C$10 -> 20000 | D7: =Assumptions!$C$10 -> 20000 | E7: =Assumptions!$C$10 -> 20000 | F7: =Assumptions!$C$10 -> 20000 | G7: =Assumptions!$C$10 -> 20000 | H7: =Assumptions!$C$10 -> 20000 | I7: =Assumptions!$C$10 -> 20000 | J7: =Assumptions!$C$10 -> 20000 | ... N7: =Assumptions!$C$10 -> 20000 | O7: =SUM(C7:N7) -> 240000
B8: Total income | C8: =IF(COUNT(C6:C7,C9,C11:C15)=0,"",C6+C7) -> 1920000 | D8: =IF(COUNT(D6:D7,D9,D11:D15)=0,"",D6+D7) -> 1977000 | E8: =IF(COUNT(E6:E7,E9,E11:E15)=0,"",E6+E7) -> 2035710 | F8: =IF(COUNT(F6:F7,F9,F11:F15)=0,"",F6+F7) -> 2096181.3 | G8: =IF(COUNT(G6:G7,G9,G11:G15)=0,"",G6+G7) -> 2158466.7 | H8: =IF(COUNT(H6:H7,H9,H11:H15)=0,"",H6+H7) -> 2222620.7 | I8: =IF(COUNT(I6:I7,I9,I11:I15)=0,"",I6+I7) -> 2288699.4 | J8: =IF(COUNT(J6:J7,J9,J11:J15)=0,"",J6+J7) -> 2356760.3 | ... N8: =IF(COUNT(N6:N7,N9,N11:N15)=0,"",N6+N7) -> 2650044.4 | O8: =SUM(C8:N8) -> 27204856
B9: Direct costs / cost of sales | C9: =C6*Assumptions!$C$11 -> 760000 | D9: =D6*Assumptions!$C$11 -> 782800 | E9: =E6*Assumptions!$C$11 -> 806284 | F9: =F6*Assumptions!$C$11 -> 830472.52 | G9: =G6*Assumptions!$C$11 -> 855386.7 | H9: =H6*Assumptions!$C$11 -> 881048.3 | I9: =I6*Assumptions!$C$11 -> 907479.75 | J9: =J6*Assumptions!$C$11 -> 934704.14 | ... N9: =N6*Assumptions!$C$11 -> 1052017.7 | O9: =SUM(C9:N9) -> 10785942
B10: Gross profit | C10: =IF(COUNT(C6:C7,C9,C11:C15)=0,"",C6-C9) -> 1140000 | D10: =IF(COUNT(D6:D7,D9,D11:D15)=0,"",D6-D9) -> 1174200 | E10: =IF(COUNT(E6:E7,E9,E11:E15)=0,"",E6-E9) -> 1209426 | F10: =IF(COUNT(F6:F7,F9,F11:F15)=0,"",F6-F9) -> 1245708.8 | G10: =IF(COUNT(G6:G7,G9,G11:G15)=0,"",G6-G9) -> 1283080 | H10: =IF(COUNT(H6:H7,H9,H11:H15)=0,"",H6-H9) -> 1321572.4 | I10: =IF(COUNT(I6:I7,I9,I11:I15)=0,"",I6-I9) -> 1361219.6 | J10: =IF(COUNT(J6:J7,J9,J11:J15)=0,"",J6-J9) -> 1402056.2 | ... N10: =IF(COUNT(N6:N7,N9,N11:N15)=0,"",N6-N9) -> 1578026.6 | O10: =SUM(C10:N10) -> 16178914
B11: Employee costs | C11: =C24*Assumptions!$C$12*IF(COLUMN()-2>=MATCH(Assumptions!$C$14,$C$5:$N$5,0),1+Assumptions!$C$13,1) -> 420000 | D11: =D24*Assumptions!$C$12*IF(COLUMN()-2>=MATCH(Assumptions!$C$14,$C$5:$N$5,0),1+Assumptions!$C$13,1) -> 420000 | E11: =E24*Assumptions!$C$12*IF(COLUMN()-2>=MATCH(Assumptions!$C$14,$C$5:$N$5,0),1+Assumptions!$C$13,1) -> 450000 | F11: =F24*Assumptions!$C$12*IF(COLUMN()-2>=MATCH(Assumptions!$C$14,$C$5:$N$5,0),1+Assumptions!$C$13,1) -> 450000 | G11: =G24*Assumptions!$C$12*IF(COLUMN()-2>=MATCH(Assumptions!$C$14,$C$5:$N$5,0),1+Assumptions!$C$13,1) -> 480000 | H11: =H24*Assumptions!$C$12*IF(COLUMN()-2>=MATCH(Assumptions!$C$14,$C$5:$N$5,0),1+Assumptions!$C$13,1) -> 480000 | I11: =I24*Assumptions!$C$12*IF(COLUMN()-2>=MATCH(Assumptions!$C$14,$C$5:$N$5,0),1+Assumptions!$C$13,1) -> 518400 | J11: =J24*Assumptions!$C$12*IF(COLUMN()-2>=MATCH(Assumptions!$C$14,$C$5:$N$5,0),1+Assumptions!$C$13,1) -> 550800 | ... N11: =N24*Assumptions!$C$12*IF(COLUMN()-2>=MATCH(Assumptions!$C$14,$C$5:$N$5,0),1+Assumptions!$C$13,1) -> 583200 | O11: =SUM(C11:N11) -> 6037200
B12: Rent & utilities | C12: =Assumptions!$C$15 -> 85000 | D12: =Assumptions!$C$15 -> 85000 | E12: =Assumptions!$C$15 -> 85000 | F12: =Assumptions!$C$15 -> 85000 | G12: =Assumptions!$C$15 -> 85000 | H12: =Assumptions!$C$15 -> 85000 | I12: =Assumptions!$C$15 -> 85000 | J12: =Assumptions!$C$15 -> 85000 | ... N12: =Assumptions!$C$15 -> 85000 | O12: =SUM(C12:N12) -> 1020000
B13: Professional & consultancy fees | C13: =Assumptions!$C$16 -> 45000 | D13: =Assumptions!$C$16 -> 45000 | E13: =Assumptions!$C$16 -> 45000 | F13: =Assumptions!$C$16 -> 45000 | G13: =Assumptions!$C$16 -> 45000 | H13: =Assumptions!$C$16 -> 45000 | I13: =Assumptions!$C$16 -> 45000 | J13: =Assumptions!$C$16 -> 45000 | ... N13: =Assumptions!$C$16 -> 45000 | O13: =SUM(C13:N13) -> 540000
B14: Sales & marketing | C14: =C6*Assumptions!$C$17 -> 57000 | D14: =D6*Assumptions!$C$17 -> 58710 | E14: =E6*Assumptions!$C$17 -> 60471.3 | F14: =F6*Assumptions!$C$17 -> 62285.439 | G14: =G6*Assumptions!$C$17 -> 64154.002 | H14: =H6*Assumptions!$C$17 -> 66078.622 | I14: =I6*Assumptions!$C$17 -> 68060.981 | J14: =J6*Assumptions!$C$17 -> 70102.81 | ... N14: =N6*Assumptions!$C$17 -> 78901.331 | O14: =SUM(C14:N14) -> 808945.69
B15: Admin & other expenses | C15: =Assumptions!$C$18 -> 55000 | D15: =Assumptions!$C$18 -> 55000 | E15: =Assumptions!$C$18 -> 55000 | F15: =Assumptions!$C$18 -> 55000 | G15: =Assumptions!$C$18 -> 55000 | H15: =Assumptions!$C$18 -> 55000 | I15: =Assumptions!$C$18 -> 55000 | J15: =Assumptions!$C$18 -> 55000 | ... N15: =Assumptions!$C$18 -> 55000 | O15: =SUM(C15:N15) -> 660000
B16: Total operating expenses | C16: =IF(COUNT(C6:C7,C9,C11:C15)=0,"",SUM(C11:C15)) -> 662000 | D16: =IF(COUNT(D6:D7,D9,D11:D15)=0,"",SUM(D11:D15)) -> 663710 | E16: =IF(COUNT(E6:E7,E9,E11:E15)=0,"",SUM(E11:E15)) -> 695471.3 | F16: =IF(COUNT(F6:F7,F9,F11:F15)=0,"",SUM(F11:F15)) -> 697285.44 | G16: =IF(COUNT(G6:G7,G9,G11:G15)=0,"",SUM(G11:G15)) -> 729154 | H16: =IF(COUNT(H6:H7,H9,H11:H15)=0,"",SUM(H11:H15)) -> 731078.62 | I16: =IF(COUNT(I6:I7,I9,I11:I15)=0,"",SUM(I11:I15)) -> 771460.98 | J16: =IF(COUNT(J6:J7,J9,J11:J15)=0,"",SUM(J11:J15)) -> 805902.81 | ... N16: =IF(COUNT(N6:N7,N9,N11:N15)=0,"",SUM(N11:N15)) -> 847101.33 | O16: =SUM(C16:N16) -> 9066145.7
B17: EBITDA | C17: =IF(COUNT(C6:C7,C9,C11:C15)=0,"",C8-C9-C16) -> 498000 | D17: =IF(COUNT(D6:D7,D9,D11:D15)=0,"",D8-D9-D16) -> 530490 | E17: =IF(COUNT(E6:E7,E9,E11:E15)=0,"",E8-E9-E16) -> 533954.7 | F17: =IF(COUNT(F6:F7,F9,F11:F15)=0,"",F8-F9-F16) -> 568423.34 | G17: =IF(COUNT(G6:G7,G9,G11:G15)=0,"",G8-G9-G16) -> 573926.04 | H17: =IF(COUNT(H6:H7,H9,H11:H15)=0,"",H8-H9-H16) -> 610493.82 | I17: =IF(COUNT(I6:I7,I9,I11:I15)=0,"",I8-I9-I16) -> 609758.64 | J17: =IF(COUNT(J6:J7,J9,J11:J15)=0,"",J8-J9-J16) -> 616153.4 | ... N17: =IF(COUNT(N6:N7,N9,N11:N15)=0,"",N8-N9-N16) -> 750925.28 | O17: =SUM(C17:N17) -> 7352768
B18: Depreciation | C18: =Assumptions!$C$19 -> 30000 | D18: =Assumptions!$C$19 -> 30000 | E18: =Assumptions!$C$19 -> 30000 | F18: =Assumptions!$C$19 -> 30000 | G18: =Assumptions!$C$19 -> 30000 | H18: =Assumptions!$C$19 -> 30000 | I18: =Assumptions!$C$19 -> 30000 | J18: =Assumptions!$C$19 -> 30000 | ... N18: =Assumptions!$C$19 -> 30000 | O18: =SUM(C18:N18) -> 360000
B19: Finance costs | C19: =Assumptions!$C$20 -> 17000 | D19: =Assumptions!$C$20 -> 17000 | E19: =Assumptions!$C$20 -> 17000 | F19: =Assumptions!$C$20 -> 17000 | G19: =Assumptions!$C$20 -> 17000 | H19: =Assumptions!$C$20 -> 17000 | I19: =Assumptions!$C$20 -> 17000 | J19: =Assumptions!$C$20 -> 17000 | ... N19: =Assumptions!$C$20 -> 17000 | O19: =SUM(C19:N19) -> 204000
B20: Profit before tax | C20: =IF(COUNT(C6:C7,C9,C11:C15)=0,"",C17-C18-C19) -> 451000 | D20: =IF(COUNT(D6:D7,D9,D11:D15)=0,"",D17-D18-D19) -> 483490 | E20: =IF(COUNT(E6:E7,E9,E11:E15)=0,"",E17-E18-E19) -> 486954.7 | F20: =IF(COUNT(F6:F7,F9,F11:F15)=0,"",F17-F18-F19) -> 521423.34 | G20: =IF(COUNT(G6:G7,G9,G11:G15)=0,"",G17-G18-G19) -> 526926.04 | H20: =IF(COUNT(H6:H7,H9,H11:H15)=0,"",H17-H18-H19) -> 563493.82 | I20: =IF(COUNT(I6:I7,I9,I11:I15)=0,"",I17-I18-I19) -> 562758.64 | J20: =IF(COUNT(J6:J7,J9,J11:J15)=0,"",J17-J18-J19) -> 569153.4 | ... N20: =IF(COUNT(N6:N7,N9,N11:N15)=0,"",N17-N18-N19) -> 703925.28 | O20: =SUM(C20:N20) -> 6788768
B21: Tax expense | C21: =MAX(0,C20)*Assumptions!$C$21 -> 112750 | D21: =MAX(0,D20)*Assumptions!$C$21 -> 120872.5 | E21: =MAX(0,E20)*Assumptions!$C$21 -> 121738.68 | F21: =MAX(0,F20)*Assumptions!$C$21 -> 130355.84 | G21: =MAX(0,G20)*Assumptions!$C$21 -> 131731.51 | H21: =MAX(0,H20)*Assumptions!$C$21 -> 140873.46 | I21: =MAX(0,I20)*Assumptions!$C$21 -> 140689.66 | J21: =MAX(0,J20)*Assumptions!$C$21 -> 142288.35 | ... N21: =MAX(0,N20)*Assumptions!$C$21 -> 175981.32 | O21: =SUM(C21:N21) -> 1697192
B22: Net profit | C22: =IF(COUNT(C6:C7,C9,C11:C15)=0,"",C20-C21) -> 338250 | D22: =IF(COUNT(D6:D7,D9,D11:D15)=0,"",D20-D21) -> 362617.5 | E22: =IF(COUNT(E6:E7,E9,E11:E15)=0,"",E20-E21) -> 365216.03 | F22: =IF(COUNT(F6:F7,F9,F11:F15)=0,"",F20-F21) -> 391067.51 | G22: =IF(COUNT(G6:G7,G9,G11:G15)=0,"",G20-G21) -> 395194.53 | H22: =IF(COUNT(H6:H7,H9,H11:H15)=0,"",H20-H21) -> 422620.37 | I22: =IF(COUNT(I6:I7,I9,I11:I15)=0,"",I20-I21) -> 422068.98 | J22: =IF(COUNT(J6:J7,J9,J11:J15)=0,"",J20-J21) -> 426865.05 | ... N22: =IF(COUNT(N6:N7,N9,N11:N15)=0,"",N20-N21) -> 527943.96 | O22: =SUM(C22:N22) -> 5091576
B24: Headcount (input) | C24: 14 | D24: 14 | E24: 15 | F24: 15 | G24: 16 | H24: 16 | I24: 16 | J24: 17 | K24: 17 | L24: 17 | M24: 18 | N24: 18

Sheet Actuals
B2: Actuals — monthly
B3: Enter actual figures each month (blue cells)
B5: Particulars (₹) | C5: Apr-26 | D5: May-26 | E5: Jun-26 | F5: Jul-26 | G5: Aug-26 | H5: Sep-26 | I5: Oct-26 | J5: Nov-26 | K5: Dec-26 | L5: Jan-27 | M5: Feb-27 | N5: Mar-27 | O5: Full year
B6: Revenue from operations | C6: 1850000 | D6: 1925000 | E6: 1990000 | F6: 2060000 | G6: 2120000 | H6: 2205000 | O6: =SUM(C6:N6) -> 12150000
B7: Other income | C7: 25000 | D7: 18000 | E7: 22000 | F7: 30000 | G7: 21000 | H7: 26000 | O7: =SUM(C7:N7) -> 142000
B8: Total income | C8: =IF(COUNT(C6:C7,C9,C11:C15)=0,"",C6+C7) -> 1875000 | D8: =IF(COUNT(D6:D7,D9,D11:D15)=0,"",D6+D7) -> 1943000 | E8: =IF(COUNT(E6:E7,E9,E11:E15)=0,"",E6+E7) -> 2012000 | F8: =IF(COUNT(F6:F7,F9,F11:F15)=0,"",F6+F7) -> 2090000 | G8: =IF(COUNT(G6:G7,G9,G11:G15)=0,"",G6+G7) -> 2141000 | H8: =IF(COUNT(H6:H7,H9,H11:H15)=0,"",H6+H7) -> 2231000 | I8: =IF(COUNT(I6:I7,I9,I11:I15)=0,"",I6+I7) | J8: =IF(COUNT(J6:J7,J9,J11:J15)=0,"",J6+J7) | ... N8: =IF(COUNT(N6:N7,N9,N11:N15)=0,"",N6+N7) | O8: =SUM(C8:N8) -> 12292000
B9: Direct costs / cost of sales | C9: 740000 | D9: 770000 | E9: 796000 | F9: 824000 | G9: 848000 | H9: 882000 | O9: =SUM(C9:N9) -> 4860000
B10: Gross profit | C10: =IF(COUNT(C6:C7,C9,C11:C15)=0,"",C6-C9) -> 1110000 | D10: =IF(COUNT(D6:D7,D9,D11:D15)=0,"",D6-D9) -> 1155000 | E10: =IF(COUNT(E6:E7,E9,E11:E15)=0,"",E6-E9) -> 1194000 | F10: =IF(COUNT(F6:F7,F9,F11:F15)=0,"",F6-F9) -> 1236000 | G10: =IF(COUNT(G6:G7,G9,G11:G15)=0,"",G6-G9) -> 1272000 | H10: =IF(COUNT(H6:H7,H9,H11:H15)=0,"",H6-H9) -> 1323000 | I10: =IF(COUNT(I6:I7,I9,I11:I15)=0,"",I6-I9) | J10: =IF(COUNT(J6:J7,J9,J11:J15)=0,"",J6-J9) | ... N10: =IF(COUNT(N6:N7,N9,N11:N15)=0,"",N6-N9) | O10: =SUM(C10:N10) -> 7290000
B11: Employee costs | C11: 420000 | D11: 420000 | E11: 435000 | F11: 435000 | G11: 450000 | H11: 450000 | O11: =SUM(C11:N11) -> 2610000
B12: Rent & utilities | C12: 85000 | D12: 85000 | E12: 85000 | F12: 85000 | G12: 85000 | H12: 85000 | O12: =SUM(C12:N12) -> 510000
B13: Professional & consultancy fees | C13: 45000 | D13: 40000 | E13: 52000 | F13: 45000 | G13: 48000 | H13: 60000 | O13: =SUM(C13:N13) -> 290000
B14: Sales & marketing | C14: 60000 | D14: 65000 | E14: 55000 | F14: 72000 | G14: 70000 | H14: 80000 | O14: =SUM(C14:N14) -> 402000
B15: Admin & other expenses | C15: 55000 | D15: 52000 | E15: 58000 | F15: 61000 | G15: 57000 | H15: 63000 | O15: =SUM(C15:N15) -> 346000
B16: Total operating expenses | C16: =IF(COUNT(C6:C7,C9,C11:C15)=0,"",SUM(C11:C15)) -> 665000 | D16: =IF(COUNT(D6:D7,D9,D11:D15)=0,"",SUM(D11:D15)) -> 662000 | E16: =IF(COUNT(E6:E7,E9,E11:E15)=0,"",SUM(E11:E15)) -> 685000 | F16: =IF(COUNT(F6:F7,F9,F11:F15)=0,"",SUM(F11:F15)) -> 698000 | G16: =IF(COUNT(G6:G7,G9,G11:G15)=0,"",SUM(G11:G15)) -> 710000 | H16: =IF(COUNT(H6:H7,H9,H11:H15)=0,"",SUM(H11:H15)) -> 738000 | I16: =IF(COUNT(I6:I7,I9,I11:I15)=0,"",SUM(I11:I15)) | J16: =IF(COUNT(J6:J7,J9,J11:J15)=0,"",SUM(J11:J15)) | ... N16: =IF(COUNT(N6:N7,N9,N11:N15)=0,"",SUM(N11:N15)) | O16: =SUM(C16:N16) -> 4158000
B17: EBITDA | C17: =IF(COUNT(C6:C7,C9,C11:C15)=0,"",C8-C9-C16) -> 470000 | D17: =IF(COUNT(D6:D7,D9,D11:D15)=0,"",D8-D9-D16) -> 511000 | E17: =IF(COUNT(E6:E7,E9,E11:E15)=0,"",E8-E9-E16) -> 531000 | F17: =IF(COUNT(F6:F7,F9,F11:F15)=0,"",F8-F9-F16) -> 568000 | G17: =IF(COUNT(G6:G7,G9,G11:G15)=0,"",G8-G9-G16) -> 583000 | H17: =IF(COUNT(H6:H7,H9,H11:H15)=0,"",H8-H9-H16) -> 611000 | I17: =IF(COUNT(I6:I7,I9,I11:I15)=0,"",I8-I9-I16) | J17: =IF(COUNT(J6:J7,J9,J11:J15)=0,"",J8-J9-J16) | ... N17: =IF(COUNT(N6:N7,N9,N11:N15)=0,"",N8-N9-N16) | O17: =SUM(C17:N17) -> 3274000
B18: Depreciation | C18: 30000 | D18: 30000 | E18: 30000 | F18: 30000 | G18: 30000 | H18: 30000 | O18: =SUM(C18:N18) -> 180000
B19: Finance costs | C19: 18000 | D19: 18000 | E19: 17500 | F19: 17500 | G19: 17000 | H19: 17000 | O19: =SUM(C19:N19) -> 105000
B20: Profit before tax | C20: =IF(COUNT(C6:C7,C9,C11:C15)=0,"",C17-C18-C19) -> 422000 | D20: =IF(COUNT(D6:D7,D9,D11:D15)=0,"",D17-D18-D19) -> 463000 | E20: =IF(COUNT(E6:E7,E9,E11:E15)=0,"",E17-E18-E19) -> 483500 | F20: =IF(COUNT(F6:F7,F9,F11:F15)=0,"",F17-F18-F19) -> 520500 | G20: =IF(COUNT(G6:G7,G9,G11:G15)=0,"",G17-G18-G19) -> 536000 | H20: =IF(COUNT(H6:H7,H9,H11:H15)=0,"",H17-H18-H19) -> 564000 | I20: =IF(COUNT(I6:I7,I9,I11:I15)=0,"",I17-I18-I19) | J20: =IF(COUNT(J6:J7,J9,J11:J15)=0,"",J17-J18-J19) | ... N20: =IF(COUNT(N6:N7,N9,N11:N15)=0,"",N17-N18-N19) | O20: =SUM(C20:N20) -> 2989000
B21: Tax expense | C21: 105500 | D21: 115800 | E21: 120900 | F21: 130100 | G21: 134000 | H21: 141000 | O21: =SUM(C21:N21) -> 747300
B22: Net profit | C22: =IF(COUNT(C6:C7,C9,C11:C15)=0,"",C20-C21) -> 316500 | D22: =IF(COUNT(D6:D7,D9,D11:D15)=0,"",D20-D21) -> 347200 | E22: =IF(COUNT(E6:E7,E9,E11:E15)=0,"",E20-E21) -> 362600 | F22: =IF(COUNT(F6:F7,F9,F11:F15)=0,"",F20-F21) -> 390400 | G22: =IF(COUNT(G6:G7,G9,G11:G15)=0,"",G20-G21) -> 402000 | H22: =IF(COUNT(H6:H7,H9,H11:H15)=0,"",H20-H21) -> 423000 | I22: =IF(COUNT(I6:I7,I9,I11:I15)=0,"",I20-I21) | J22: =IF(COUNT(J6:J7,J9,J11:J15)=0,"",J20-J21) | ... N22: =IF(COUNT(N6:N7,N9,N11:N15)=0,"",N20-N21) | O22: =SUM(C22:N22) -> 2241700

Sheet Budget vs Actual
B2: Budget vs Actual
B3: ="Client: "&Assumptions!$C$5&" | Month: "&$C$4 -> Client: Sample Traders Pvt Ltd | Month: Sep-26
B4: Review month | C4: Sep-26 | Q4: Month index | R4: =MATCH($C$4,Budget!$C$5:$N$5,0) -> 6
B6: Particulars (₹) | C6: Budget | D6: Actual | E6: Variance | F6: Var % | H6: YTD budget | I6: YTD actual | J6: YTD variance | K6: YTD var % | L6: Nature
B7: Revenue from operations | C7: =N(INDEX(Budget!$C$6:$N$6,$R$4)) -> 2202620.7 | D7: =N(INDEX(Actuals!$C$6:$N$6,$R$4)) -> 2205000 | E7: =D7-C7 -> 2379.2588 | F7: =IF(C7=0,"",E7/ABS(C7)) -> 0.0010801945 | G7: =IF(E7=0,"-",IF((L7="Income")=(E7>0),"Favourable","Adverse")) -> Favourable | H7: =SUM(INDEX(Budget!$C$6:$N$6,1):INDEX(Budget!$C$6:$N$6,$R$4)) -> 12289979 | I7: =SUM(INDEX(Actuals!$C$6:$N$6,1):INDEX(Actuals!$C$6:$N$6,$R$4)) -> 12150000 | J7: =I7-H7 -> -139978.78 | K7: =IF(H7=0,"",J7/ABS(H7)) -> -0.011389668 | L7: Income
B8: Other income | C8: =N(INDEX(Budget!$C$7:$N$7,$R$4)) -> 20000 | D8: =N(INDEX(Actuals!$C$7:$N$7,$R$4)) -> 26000 | E8: =D8-C8 -> 6000 | F8: =IF(C8=0,"",E8/ABS(C8)) -> 0.3 | G8: =IF(E8=0,"-",IF((L8="Income")=(E8>0),"Favourable","Adverse")) -> Favourable | H8: =SUM(INDEX(Budget!$C$7:$N$7,1):INDEX(Budget!$C$7:$N$7,$R$4)) -> 120000 | I8: =SUM(INDEX(Actuals!$C$7:$N$7,1):INDEX(Actuals!$C$7:$N$7,$R$4)) -> 142000 | J8: =I8-H8 -> 22000 | K8: =IF(H8=0,"",J8/ABS(H8)) -> 0.18333333 | L8: Income
B9: Total income | C9: =N(INDEX(Budget!$C$8:$N$8,$R$4)) -> 2222620.7 | D9: =N(INDEX(Actuals!$C$8:$N$8,$R$4)) -> 2231000 | E9: =D9-C9 -> 8379.2588 | F9: =IF(C9=0,"",E9/ABS(C9)) -> 0.0037699904 | G9: =IF(E9=0,"-",IF((L9="Income")=(E9>0),"Favourable","Adverse")) -> Favourable | H9: =SUM(INDEX(Budget!$C$8:$N$8,1):INDEX(Budget!$C$8:$N$8,$R$4)) -> 12409979 | I9: =SUM(INDEX(Actuals!$C$8:$N$8,1):INDEX(Actuals!$C$8:$N$8,$R$4)) -> 12292000 | J9: =I9-H9 -> -117978.78 | K9: =IF(H9=0,"",J9/ABS(H9)) -> -0.0095067673 | L9: Income
B10: Direct costs / cost of sales | C10: =N(INDEX(Budget!$C$9:$N$9,$R$4)) -> 881048.3 | D10: =N(INDEX(Actuals!$C$9:$N$9,$R$4)) -> 882000 | E10: =D10-C10 -> 951.70353 | F10: =IF(C10=0,"",E10/ABS(C10)) -> 0.0010801945 | G10: =IF(E10=0,"-",IF((L10="Income")=(E10>0),"Favourable","Adverse")) -> Adverse | H10: =SUM(INDEX(Budget!$C$9:$N$9,1):INDEX(Budget!$C$9:$N$9,$R$4)) -> 4915991.5 | I10: =SUM(INDEX(Actuals!$C$9:$N$9,1):INDEX(Actuals!$C$9:$N$9,$R$4)) -> 4860000 | J10: =I10-H10 -> -55991.512 | K10: =IF(H10=0,"",J10/ABS(H10)) -> -0.011389668 | L10: Cost
B11: Gross profit | C11: =N(INDEX(Budget!$C$10:$N$10,$R$4)) -> 1321572.4 | D11: =N(INDEX(Actuals!$C$10:$N$10,$R$4)) -> 1323000 | E11: =D11-C11 -> 1427.5553 | F11: =IF(C11=0,"",E11/ABS(C11)) -> 0.0010801945 | G11: =IF(E11=0,"-",IF((L11="Income")=(E11>0),"Favourable","Adverse")) -> Favourable | H11: =SUM(INDEX(Budget!$C$10:$N$10,1):INDEX(Budget!$C$10:$N$10,$R$4)) -> 7373987.3 | I11: =SUM(INDEX(Actuals!$C$10:$N$10,1):INDEX(Actuals!$C$10:$N$10,$R$4)) -> 7290000 | J11: =I11-H11 -> -83987.268 | K11: =IF(H11=0,"",J11/ABS(H11)) -> -0.011389668 | L11: Income
B12: Employee costs | C12: =N(INDEX(Budget!$C$11:$N$11,$R$4)) -> 480000 | D12: =N(INDEX(Actuals!$C$11:$N$11,$R$4)) -> 450000 | E12: =D12-C12 -> -30000 | F12: =IF(C12=0,"",E12/ABS(C12)) -> -0.0625 | G12: =IF(E12=0,"-",IF((L12="Income")=(E12>0),"Favourable","Adverse")) -> Favourable | H12: =SUM(INDEX(Budget!$C$11:$N$11,1):INDEX(Budget!$C$11:$N$11,$R$4)) -> 2700000 | I12: =SUM(INDEX(Actuals!$C$11:$N$11,1):INDEX(Actuals!$C$11:$N$11,$R$4)) -> 2610000 | J12: =I12-H12 -> -90000 | K12: =IF(H12=0,"",J12/ABS(H12)) -> -0.033333333 | L12: Cost
B13: Rent & utilities | C13: =N(INDEX(Budget!$C$12:$N$12,$R$4)) -> 85000 | D13: =N(INDEX(Actuals!$C$12:$N$12,$R$4)) -> 85000 | E13: =D13-C13 -> 0 | F13: =IF(C13=0,"",E13/ABS(C13)) -> 0 | G13: =IF(E13=0,"-",IF((L13="Income")=(E13>0),"Favourable","Adverse")) -> - | H13: =SUM(INDEX(Budget!$C$12:$N$12,1):INDEX(Budget!$C$12:$N$12,$R$4)) -> 510000 | I13: =SUM(INDEX(Actuals!$C$12:$N$12,1):INDEX(Actuals!$C$12:$N$12,$R$4)) -> 510000 | J13: =I13-H13 -> 0 | K13: =IF(H13=0,"",J13/ABS(H13)) -> 0 | L13: Cost
B14: Professional & consultancy fees | C14: =N(INDEX(Budget!$C$13:$N$13,$R$4)) -> 45000 | D14: =N(INDEX(Actuals!$C$13:$N$13,$R$4)) -> 60000 | E14: =D14-C14 -> 15000 | F14: =IF(C14=0,"",E14/ABS(C14)) -> 0.33333333 | G14: =IF(E14=0,"-",IF((L14="Income")=(E14>0),"Favourable","Adverse")) -> Adverse | H14: =SUM(INDEX(Budget!$C$13:$N$13,1):INDEX(Budget!$C$13:$N$13,$R$4)) -> 270000 | I14: =SUM(INDEX(Actuals!$C$13:$N$13,1):INDEX(Actuals!$C$13:$N$13,$R$4)) -> 290000 | J14: =I14-H14 -> 20000 | K14: =IF(H14=0,"",J14/ABS(H14)) -> 0.074074074 | L14: Cost
B15: Sales & marketing | C15: =N(INDEX(Budget!$C$14:$N$14,$R$4)) -> 66078.622 | D15: =N(INDEX(Actuals!$C$14:$N$14,$R$4)) -> 80000 | E15: =D15-C15 -> 13921.378 | F15: =IF(C15=0,"",E15/ABS(C15)) -> 0.210679 | G15: =IF(E15=0,"-",IF((L15="Income")=(E15>0),"Favourable","Adverse")) -> Adverse | H15: =SUM(INDEX(Budget!$C$14:$N$14,1):INDEX(Budget!$C$14:$N$14,$R$4)) -> 368699.36 | I15: =SUM(INDEX(Actuals!$C$14:$N$14,1):INDEX(Actuals!$C$14:$N$14,$R$4)) -> 402000 | J15: =I15-H15 -> 33300.637 | K15: =IF(H15=0,"",J15/ABS(H15)) -> 0.090319214 | L15: Cost
B16: Admin & other expenses | C16: =N(INDEX(Budget!$C$15:$N$15,$R$4)) -> 55000 | D16: =N(INDEX(Actuals!$C$15:$N$15,$R$4)) -> 63000 | E16: =D16-C16 -> 8000 | F16: =IF(C16=0,"",E16/ABS(C16)) -> 0.14545455 | G16: =IF(E16=0,"-",IF((L16="Income")=(E16>0),"Favourable","Adverse")) -> Adverse | H16: =SUM(INDEX(Budget!$C$15:$N$15,1):INDEX(Budget!$C$15:$N$15,$R$4)) -> 330000 | I16: =SUM(INDEX(Actuals!$C$15:$N$15,1):INDEX(Actuals!$C$15:$N$15,$R$4)) -> 346000 | J16: =I16-H16 -> 16000 | K16: =IF(H16=0,"",J16/ABS(H16)) -> 0.048484848 | L16: Cost
B17: Total operating expenses | C17: =N(INDEX(Budget!$C$16:$N$16,$R$4)) -> 731078.62 | D17: =N(INDEX(Actuals!$C$16:$N$16,$R$4)) -> 738000 | E17: =D17-C17 -> 6921.3778 | F17: =IF(C17=0,"",E17/ABS(C17)) -> 0.0094673508 | G17: =IF(E17=0,"-",IF((L17="Income")=(E17>0),"Favourable","Adverse")) -> Adverse | H17: =SUM(INDEX(Budget!$C$16:$N$16,1):INDEX(Budget!$C$16:$N$16,$R$4)) -> 4178699.4 | I17: =SUM(INDEX(Actuals!$C$16:$N$16,1):INDEX(Actuals!$C$16:$N$16,$R$4)) -> 4158000 | J17: =I17-H17 -> -20699.363 | K17: =IF(H17=0,"",J17/ABS(H17)) -> -0.0049535421 | L17: Cost
B18: EBITDA | C18: =N(INDEX(Budget!$C$17:$N$17,$R$4)) -> 610493.82 | D18: =N(INDEX(Actuals!$C$17:$N$17,$R$4)) -> 611000 | E18: =D18-C18 -> 506.17753 | F18: =IF(C18=0,"",E18/ABS(C18)) -> 0.00082912802 | G18: =IF(E18=0,"-",IF((L18="Income")=(E18>0),"Favourable","Adverse")) -> Favourable | H18: =SUM(INDEX(Budget!$C$17:$N$17,1):INDEX(Budget!$C$17:$N$17,$R$4)) -> 3315287.9 | I18: =SUM(INDEX(Actuals!$C$17:$N$17,1):INDEX(Actuals!$C$17:$N$17,$R$4)) -> 3274000 | J18: =I18-H18 -> -41287.905 | K18: =IF(H18=0,"",J18/ABS(H18)) -> -0.012453792 | L18: Income
B19: Depreciation | C19: =N(INDEX(Budget!$C$18:$N$18,$R$4)) -> 30000 | D19: =N(INDEX(Actuals!$C$18:$N$18,$R$4)) -> 30000 | E19: =D19-C19 -> 0 | F19: =IF(C19=0,"",E19/ABS(C19)) -> 0 | G19: =IF(E19=0,"-",IF((L19="Income")=(E19>0),"Favourable","Adverse")) -> - | H19: =SUM(INDEX(Budget!$C$18:$N$18,1):INDEX(Budget!$C$18:$N$18,$R$4)) -> 180000 | I19: =SUM(INDEX(Actuals!$C$18:$N$18,1):INDEX(Actuals!$C$18:$N$18,$R$4)) -> 180000 | J19: =I19-H19 -> 0 | K19: =IF(H19=0,"",J19/ABS(H19)) -> 0 | L19: Cost
B20: Finance costs | C20: =N(INDEX(Budget!$C$19:$N$19,$R$4)) -> 17000 | D20: =N(INDEX(Actuals!$C$19:$N$19,$R$4)) -> 17000 | E20: =D20-C20 -> 0 | F20: =IF(C20=0,"",E20/ABS(C20)) -> 0 | G20: =IF(E20=0,"-",IF((L20="Income")=(E20>0),"Favourable","Adverse")) -> - | H20: =SUM(INDEX(Budget!$C$19:$N$19,1):INDEX(Budget!$C$19:$N$19,$R$4)) -> 102000 | I20: =SUM(INDEX(Actuals!$C$19:$N$19,1):INDEX(Actuals!$C$19:$N$19,$R$4)) -> 105000 | J20: =I20-H20 -> 3000 | K20: =IF(H20=0,"",J20/ABS(H20)) -> 0.029411765 | L20: Cost
B21: Profit before tax | C21: =N(INDEX(Budget!$C$20:$N$20,$R$4)) -> 563493.82 | D21: =N(INDEX(Actuals!$C$20:$N$20,$R$4)) -> 564000 | E21: =D21-C21 -> 506.17753 | F21: =IF(C21=0,"",E21/ABS(C21)) -> 0.00089828409 | G21: =IF(E21=0,"-",IF((L21="Income")=(E21>0),"Favourable","Adverse")) -> Favourable | H21: =SUM(INDEX(Budget!$C$20:$N$20,1):INDEX(Budget!$C$20:$N$20,$R$4)) -> 3033287.9 | I21: =SUM(INDEX(Actuals!$C$20:$N$20,1):INDEX(Actuals!$C$20:$N$20,$R$4)) -> 2989000 | J21: =I21-H21 -> -44287.905 | K21: =IF(H21=0,"",J21/ABS(H21)) -> -0.014600627 | L21: Income
B22: Tax expense | C22: =N(INDEX(Budget!$C$21:$N$21,$R$4)) -> 140873.46 | D22: =N(INDEX(Actuals!$C$21:$N$21,$R$4)) -> 141000 | E22: =D22-C22 -> 126.54438 | F22: =IF(C22=0,"",E22/ABS(C22)) -> 0.00089828409 | G22: =IF(E22=0,"-",IF((L22="Income")=(E22>0),"Favourable","Adverse")) -> Adverse | H22: =SUM(INDEX(Budget!$C$21:$N$21,1):INDEX(Budget!$C$21:$N$21,$R$4)) -> 758321.98 | I22: =SUM(INDEX(Actuals!$C$21:$N$21,1):INDEX(Actuals!$C$21:$N$21,$R$4)) -> 747300 | J22: =I22-H22 -> -11021.976 | K22: =IF(H22=0,"",J22/ABS(H22)) -> -0.014534692 | L22: Cost
B23: Net profit | C23: =N(INDEX(Budget!$C$22:$N$22,$R$4)) -> 422620.37 | D23: =N(INDEX(Actuals!$C$22:$N$22,$R$4)) -> 423000 | E23: =D23-C23 -> 379.63315 | F23: =IF(C23=0,"",E23/ABS(C23)) -> 0.00089828409 | G23: =IF(E23=0,"-",IF((L23="Income")=(E23>0),"Favourable","Adverse")) -> Favourable | H23: =SUM(INDEX(Budget!$C$22:$N$22,1):INDEX(Budget!$C$22:$N$22,$R$4)) -> 2274965.9 | I23: =SUM(INDEX(Actuals!$C$22:$N$22,1):INDEX(Actuals!$C$22:$N$22,$R$4)) -> 2241700 | J23: =I23-H23 -> -33265.929 | K23: =IF(H23=0,"",J23/ABS(H23)) -> -0.014622605 | L23: Income

Sheet Rolling Forecast
B2: Rolling forecast — latest estimate for the year | R2: =MATCH(Assumptions!$C$23,Budget!$C$5:$N$5,0) -> 6
B3: ="Last closed month: "&Assumptions!$C$23&" (change it on Assumptions)" -> Last closed month: Sep-26 (change it on Assumptions)
B4: Source | C4: =IF(1<=$R$2,"Actual","Forecast") -> Actual | D4: =IF(2<=$R$2,"Actual","Forecast") -> Actual | E4: =IF(3<=$R$2,"Actual","Forecast") -> Actual | F4: =IF(4<=$R$2,"Actual","Forecast") -> Actual | G4: =IF(5<=$R$2,"Actual","Forecast") -> Actual | H4: =IF(6<=$R$2,"Actual","Forecast") -> Actual | I4: =IF(7<=$R$2,"Actual","Forecast") -> Forecast | J4: =IF(8<=$R$2,"Actual","Forecast") -> Forecast | K4: =IF(9<=$R$2,"Actual","Forecast") -> Forecast | L4: =IF(10<=$R$2,"Actual","Forecast") -> Forecast | M4: =IF(11<=$R$2,"Actual","Forecast") -> Forecast | N4: =IF(12<=$R$2,"Actual","Forecast") -> Forecast
B5: Particulars (₹) | C5: Apr-26 | D5: May-26 | E5: Jun-26 | F5: Jul-26 | G5: Aug-26 | H5: Sep-26 | I5: Oct-26 | J5: Nov-26 | K5: Dec-26 | L5: Jan-27 | M5: Feb-27 | N5: Mar-27 | O5: Latest estimate | P5: Annual budget | Q5: Variance | R5: Var %
B6: Revenue from operations | C6: =IF(1<=$R$2,N(Actuals!C6),Budget!C6) -> 1850000 | D6: =IF(2<=$R$2,N(Actuals!D6),Budget!D6) -> 1925000 | E6: =IF(3<=$R$2,N(Actuals!E6),Budget!E6) -> 1990000 | F6: =IF(4<=$R$2,N(Actuals!F6),Budget!F6) -> 2060000 | G6: =IF(5<=$R$2,N(Actuals!G6),Budget!G6) -> 2120000 | H6: =IF(6<=$R$2,N(Actuals!H6),Budget!H6) -> 2205000 | I6: =IF(7<=$R$2,N(Actuals!I6),Budget!I6) -> 2268699.4 | J6: =IF(8<=$R$2,N(Actuals!J6),Budget!J6) -> 2336760.3 | K6: =IF(9<=$R$2,N(Actuals!K6),Budget!K6) -> 2406863.2 | L6: =IF(10<=$R$2,N(Actuals!L6),Budget!L6) -> 2479069 | M6: =IF(11<=$R$2,N(Actuals!M6),Budget!M6) -> 2553441.1 | N6: =IF(12<=$R$2,N(Actuals!N6),Budget!N6) -> 2630044.4 | O6: =SUM(C6:N6) -> 26824877 | P6: =Budget!O6 -> 26964856 | Q6: =O6-P6 -> -139978.78 | R6: =IF(P6=0,"",Q6/ABS(P6)) -> -0.0051911562
B7: Other income | C7: =IF(1<=$R$2,N(Actuals!C7),Budget!C7) -> 25000 | D7: =IF(2<=$R$2,N(Actuals!D7),Budget!D7) -> 18000 | E7: =IF(3<=$R$2,N(Actuals!E7),Budget!E7) -> 22000 | F7: =IF(4<=$R$2,N(Actuals!F7),Budget!F7) -> 30000 | G7: =IF(5<=$R$2,N(Actuals!G7),Budget!G7) -> 21000 | H7: =IF(6<=$R$2,N(Actuals!H7),Budget!H7) -> 26000 | I7: =IF(7<=$R$2,N(Actuals!I7),Budget!I7) -> 20000 | J7: =IF(8<=$R$2,N(Actuals!J7),Budget!J7) -> 20000 | K7: =IF(9<=$R$2,N(Actuals!K7),Budget!K7) -> 20000 | L7: =IF(10<=$R$2,N(Actuals!L7),Budget!L7) -> 20000 | M7: =IF(11<=$R$2,N(Actuals!M7),Budget!M7) -> 20000 | N7: =IF(12<=$R$2,N(Actuals!N7),Budget!N7) -> 20000 | O7: =SUM(C7:N7) -> 262000 | P7: =Budget!O7 -> 240000 | Q7: =O7-P7 -> 22000 | R7: =IF(P7=0,"",Q7/ABS(P7)) -> 0.091666667
B8: Total income | C8: =IF(COUNT(C6:C7,C9,C11:C15)=0,"",C6+C7) -> 1875000 | D8: =IF(COUNT(D6:D7,D9,D11:D15)=0,"",D6+D7) -> 1943000 | E8: =IF(COUNT(E6:E7,E9,E11:E15)=0,"",E6+E7) -> 2012000 | F8: =IF(COUNT(F6:F7,F9,F11:F15)=0,"",F6+F7) -> 2090000 | G8: =IF(COUNT(G6:G7,G9,G11:G15)=0,"",G6+G7) -> 2141000 | H8: =IF(COUNT(H6:H7,H9,H11:H15)=0,"",H6+H7) -> 2231000 | I8: =IF(COUNT(I6:I7,I9,I11:I15)=0,"",I6+I7) -> 2288699.4 | J8: =IF(COUNT(J6:J7,J9,J11:J15)=0,"",J6+J7) -> 2356760.3 | ... N8: =IF(COUNT(N6:N7,N9,N11:N15)=0,"",N6+N7) -> 2650044.4 | O8: =SUM(C8:N8) -> 27086877 | P8: =Budget!O8 -> 27204856 | Q8: =O8-P8 -> -117978.78 | R8: =IF(P8=0,"",Q8/ABS(P8)) -> -0.0043366809
B9: Direct costs / cost of sales | C9: =IF(1<=$R$2,N(Actuals!C9),Budget!C9) -> 740000 | D9: =IF(2<=$R$2,N(Actuals!D9),Budget!D9) -> 770000 | E9: =IF(3<=$R$2,N(Actuals!E9),Budget!E9) -> 796000 | F9: =IF(4<=$R$2,N(Actuals!F9),Budget!F9) -> 824000 | G9: =IF(5<=$R$2,N(Actuals!G9),Budget!G9) -> 848000 | H9: =IF(6<=$R$2,N(Actuals!H9),Budget!H9) -> 882000 | I9: =IF(7<=$R$2,N(Actuals!I9),Budget!I9) -> 907479.75 | J9: =IF(8<=$R$2,N(Actuals!J9),Budget!J9) -> 934704.14 | K9: =IF(9<=$R$2,N(Actuals!K9),Budget!K9) -> 962745.26 | L9: =IF(10<=$R$2,N(Actuals!L9),Budget!L9) -> 991627.62 | M9: =IF(11<=$R$2,N(Actuals!M9),Budget!M9) -> 1021376.4 | N9: =IF(12<=$R$2,N(Actuals!N9),Budget!N9) -> 1052017.7 | O9: =SUM(C9:N9) -> 10729951 | P9: =Budget!O9 -> 10785942 | Q9: =O9-P9 -> -55991.512 | R9: =IF(P9=0,"",Q9/ABS(P9)) -> -0.0051911562
B10: Gross profit | C10: =IF(COUNT(C6:C7,C9,C11:C15)=0,"",C6-C9) -> 1110000 | D10: =IF(COUNT(D6:D7,D9,D11:D15)=0,"",D6-D9) -> 1155000 | E10: =IF(COUNT(E6:E7,E9,E11:E15)=0,"",E6-E9) -> 1194000 | F10: =IF(COUNT(F6:F7,F9,F11:F15)=0,"",F6-F9) -> 1236000 | G10: =IF(COUNT(G6:G7,G9,G11:G15)=0,"",G6-G9) -> 1272000 | H10: =IF(COUNT(H6:H7,H9,H11:H15)=0,"",H6-H9) -> 1323000 | I10: =IF(COUNT(I6:I7,I9,I11:I15)=0,"",I6-I9) -> 1361219.6 | J10: =IF(COUNT(J6:J7,J9,J11:J15)=0,"",J6-J9) -> 1402056.2 | ... N10: =IF(COUNT(N6:N7,N9,N11:N15)=0,"",N6-N9) -> 1578026.6 | O10: =SUM(C10:N10) -> 16094926 | P10: =Budget!O10 -> 16178914 | Q10: =O10-P10 -> -83987.268 | R10: =IF(P10=0,"",Q10/ABS(P10)) -> -0.0051911562
B11: Employee costs | C11: =IF(1<=$R$2,N(Actuals!C11),Budget!C11) -> 420000 | D11: =IF(2<=$R$2,N(Actuals!D11),Budget!D11) -> 420000 | E11: =IF(3<=$R$2,N(Actuals!E11),Budget!E11) -> 435000 | F11: =IF(4<=$R$2,N(Actuals!F11),Budget!F11) -> 435000 | G11: =IF(5<=$R$2,N(Actuals!G11),Budget!G11) -> 450000 | H11: =IF(6<=$R$2,N(Actuals!H11),Budget!H11) -> 450000 | I11: =IF(7<=$R$2,N(Actuals!I11),Budget!I11) -> 518400 | J11: =IF(8<=$R$2,N(Actuals!J11),Budget!J11) -> 550800 | K11: =IF(9<=$R$2,N(Actuals!K11),Budget!K11) -> 550800 | L11: =IF(10<=$R$2,N(Actuals!L11),Budget!L11) -> 550800 | M11: =IF(11<=$R$2,N(Actuals!M11),Budget!M11) -> 583200 | N11: =IF(12<=$R$2,N(Actuals!N11),Budget!N11) -> 583200 | O11: =SUM(C11:N11) -> 5947200 | P11: =Budget!O11 -> 6037200 | Q11: =O11-P11 -> -90000 | R11: =IF(P11=0,"",Q11/ABS(P11)) -> -0.014907573
B12: Rent & utilities | C12: =IF(1<=$R$2,N(Actuals!C12),Budget!C12) -> 85000 | D12: =IF(2<=$R$2,N(Actuals!D12),Budget!D12) -> 85000 | E12: =IF(3<=$R$2,N(Actuals!E12),Budget!E12) -> 85000 | F12: =IF(4<=$R$2,N(Actuals!F12),Budget!F12) -> 85000 | G12: =IF(5<=$R$2,N(Actuals!G12),Budget!G12) -> 85000 | H12: =IF(6<=$R$2,N(Actuals!H12),Budget!H12) -> 85000 | I12: =IF(7<=$R$2,N(Actuals!I12),Budget!I12) -> 85000 | J12: =IF(8<=$R$2,N(Actuals!J12),Budget!J12) -> 85000 | K12: =IF(9<=$R$2,N(Actuals!K12),Budget!K12) -> 85000 | L12: =IF(10<=$R$2,N(Actuals!L12),Budget!L12) -> 85000 | M12: =IF(11<=$R$2,N(Actuals!M12),Budget!M12) -> 85000 | N12: =IF(12<=$R$2,N(Actuals!N12),Budget!N12) -> 85000 | O12: =SUM(C12:N12) -> 1020000 | P12: =Budget!O12 -> 1020000 | Q12: =O12-P12 -> 0 | R12: =IF(P12=0,"",Q12/ABS(P12)) -> 0
B13: Professional & consultancy fees | C13: =IF(1<=$R$2,N(Actuals!C13),Budget!C13) -> 45000 | D13: =IF(2<=$R$2,N(Actuals!D13),Budget!D13) -> 40000 | E13: =IF(3<=$R$2,N(Actuals!E13),Budget!E13) -> 52000 | F13: =IF(4<=$R$2,N(Actuals!F13),Budget!F13) -> 45000 | G13: =IF(5<=$R$2,N(Actuals!G13),Budget!G13) -> 48000 | H13: =IF(6<=$R$2,N(Actuals!H13),Budget!H13) -> 60000 | I13: =IF(7<=$R$2,N(Actuals!I13),Budget!I13) -> 45000 | J13: =IF(8<=$R$2,N(Actuals!J13),Budget!J13) -> 45000 | K13: =IF(9<=$R$2,N(Actuals!K13),Budget!K13) -> 45000 | L13: =IF(10<=$R$2,N(Actuals!L13),Budget!L13) -> 45000 | M13: =IF(11<=$R$2,N(Actuals!M13),Budget!M13) -> 45000 | N13: =IF(12<=$R$2,N(Actuals!N13),Budget!N13) -> 45000 | O13: =SUM(C13:N13) -> 560000 | P13: =Budget!O13 -> 540000 | Q13: =O13-P13 -> 20000 | R13: =IF(P13=0,"",Q13/ABS(P13)) -> 0.037037037
B14: Sales & marketing | C14: =IF(1<=$R$2,N(Actuals!C14),Budget!C14) -> 60000 | D14: =IF(2<=$R$2,N(Actuals!D14),Budget!D14) -> 65000 | E14: =IF(3<=$R$2,N(Actuals!E14),Budget!E14) -> 55000 | F14: =IF(4<=$R$2,N(Actuals!F14),Budget!F14) -> 72000 | G14: =IF(5<=$R$2,N(Actuals!G14),Budget!G14) -> 70000 | H14: =IF(6<=$R$2,N(Actuals!H14),Budget!H14) -> 80000 | I14: =IF(7<=$R$2,N(Actuals!I14),Budget!I14) -> 68060.981 | J14: =IF(8<=$R$2,N(Actuals!J14),Budget!J14) -> 70102.81 | K14: =IF(9<=$R$2,N(Actuals!K14),Budget!K14) -> 72205.895 | L14: =IF(10<=$R$2,N(Actuals!L14),Budget!L14) -> 74372.071 | M14: =IF(11<=$R$2,N(Actuals!M14),Budget!M14) -> 76603.234 | N14: =IF(12<=$R$2,N(Actuals!N14),Budget!N14) -> 78901.331 | O14: =SUM(C14:N14) -> 842246.32 | P14: =Budget!O14 -> 808945.69 | Q14: =O14-P14 -> 33300.637 | R14: =IF(P14=0,"",Q14/ABS(P14)) -> 0.041165479
B15: Admin & other expenses | C15: =IF(1<=$R$2,N(Actuals!C15),Budget!C15) -> 55000 | D15: =IF(2<=$R$2,N(Actuals!D15),Budget!D15) -> 52000 | E15: =IF(3<=$R$2,N(Actuals!E15),Budget!E15) -> 58000 | F15: =IF(4<=$R$2,N(Actuals!F15),Budget!F15) -> 61000 | G15: =IF(5<=$R$2,N(Actuals!G15),Budget!G15) -> 57000 | H15: =IF(6<=$R$2,N(Actuals!H15),Budget!H15) -> 63000 | I15: =IF(7<=$R$2,N(Actuals!I15),Budget!I15) -> 55000 | J15: =IF(8<=$R$2,N(Actuals!J15),Budget!J15) -> 55000 | K15: =IF(9<=$R$2,N(Actuals!K15),Budget!K15) -> 55000 | L15: =IF(10<=$R$2,N(Actuals!L15),Budget!L15) -> 55000 | M15: =IF(11<=$R$2,N(Actuals!M15),Budget!M15) -> 55000 | N15: =IF(12<=$R$2,N(Actuals!N15),Budget!N15) -> 55000 | O15: =SUM(C15:N15) -> 676000 | P15: =Budget!O15 -> 660000 | Q15: =O15-P15 -> 16000 | R15: =IF(P15=0,"",Q15/ABS(P15)) -> 0.024242424
B16: Total operating expenses | C16: =IF(COUNT(C6:C7,C9,C11:C15)=0,"",SUM(C11:C15)) -> 665000 | D16: =IF(COUNT(D6:D7,D9,D11:D15)=0,"",SUM(D11:D15)) -> 662000 | E16: =IF(COUNT(E6:E7,E9,E11:E15)=0,"",SUM(E11:E15)) -> 685000 | F16: =IF(COUNT(F6:F7,F9,F11:F15)=0,"",SUM(F11:F15)) -> 698000 | G16: =IF(COUNT(G6:G7,G9,G11:G15)=0,"",SUM(G11:G15)) -> 710000 | H16: =IF(COUNT(H6:H7,H9,H11:H15)=0,"",SUM(H11:H15)) -> 738000 | I16: =IF(COUNT(I6:I7,I9,I11:I15)=0,"",SUM(I11:I15)) -> 771460.98 | J16: =IF(COUNT(J6:J7,J9,J11:J15)=0,"",SUM(J11:J15)) -> 805902.81 | ... N16: =IF(COUNT(N6:N7,N9,N11:N15)=0,"",SUM(N11:N15)) -> 847101.33 | O16: =SUM(C16:N16) -> 9045446.3 | P16: =Budget!O16 -> 9066145.7 | Q16: =O16-P16 -> -20699.363 | R16: =IF(P16=0,"",Q16/ABS(P16)) -> -0.0022831492
B17: EBITDA | C17: =IF(COUNT(C6:C7,C9,C11:C15)=0,"",C8-C9-C16) -> 470000 | D17: =IF(COUNT(D6:D7,D9,D11:D15)=0,"",D8-D9-D16) -> 511000 | E17: =IF(COUNT(E6:E7,E9,E11:E15)=0,"",E8-E9-E16) -> 531000 | F17: =IF(COUNT(F6:F7,F9,F11:F15)=0,"",F8-F9-F16) -> 568000 | G17: =IF(COUNT(G6:G7,G9,G11:G15)=0,"",G8-G9-G16) -> 583000 | H17: =IF(COUNT(H6:H7,H9,H11:H15)=0,"",H8-H9-H16) -> 611000 | I17: =IF(COUNT(I6:I7,I9,I11:I15)=0,"",I8-I9-I16) -> 609758.64 | J17: =IF(COUNT(J6:J7,J9,J11:J15)=0,"",J8-J9-J16) -> 616153.4 | ... N17: =IF(COUNT(N6:N7,N9,N11:N15)=0,"",N8-N9-N16) -> 750925.28 | O17: =SUM(C17:N17) -> 7311480.1 | P17: =Budget!O17 -> 7352768 | Q17: =O17-P17 -> -41287.905 | R17: =IF(P17=0,"",Q17/ABS(P17)) -> -0.0056152873
B18: Depreciation | C18: =IF(1<=$R$2,N(Actuals!C18),Budget!C18) -> 30000 | D18: =IF(2<=$R$2,N(Actuals!D18),Budget!D18) -> 30000 | E18: =IF(3<=$R$2,N(Actuals!E18),Budget!E18) -> 30000 | F18: =IF(4<=$R$2,N(Actuals!F18),Budget!F18) -> 30000 | G18: =IF(5<=$R$2,N(Actuals!G18),Budget!G18) -> 30000 | H18: =IF(6<=$R$2,N(Actuals!H18),Budget!H18) -> 30000 | I18: =IF(7<=$R$2,N(Actuals!I18),Budget!I18) -> 30000 | J18: =IF(8<=$R$2,N(Actuals!J18),Budget!J18) -> 30000 | K18: =IF(9<=$R$2,N(Actuals!K18),Budget!K18) -> 30000 | L18: =IF(10<=$R$2,N(Actuals!L18),Budget!L18) -> 30000 | M18: =IF(11<=$R$2,N(Actuals!M18),Budget!M18) -> 30000 | N18: =IF(12<=$R$2,N(Actuals!N18),Budget!N18) -> 30000 | O18: =SUM(C18:N18) -> 360000 | P18: =Budget!O18 -> 360000 | Q18: =O18-P18 -> 0 | R18: =IF(P18=0,"",Q18/ABS(P18)) -> 0
B19: Finance costs | C19: =IF(1<=$R$2,N(Actuals!C19),Budget!C19) -> 18000 | D19: =IF(2<=$R$2,N(Actuals!D19),Budget!D19) -> 18000 | E19: =IF(3<=$R$2,N(Actuals!E19),Budget!E19) -> 17500 | F19: =IF(4<=$R$2,N(Actuals!F19),Budget!F19) -> 17500 | G19: =IF(5<=$R$2,N(Actuals!G19),Budget!G19) -> 17000 | H19: =IF(6<=$R$2,N(Actuals!H19),Budget!H19) -> 17000 | I19: =IF(7<=$R$2,N(Actuals!I19),Budget!I19) -> 17000 | J19: =IF(8<=$R$2,N(Actuals!J19),Budget!J19) -> 17000 | K19: =IF(9<=$R$2,N(Actuals!K19),Budget!K19) -> 17000 | L19: =IF(10<=$R$2,N(Actuals!L19),Budget!L19) -> 17000 | M19: =IF(11<=$R$2,N(Actuals!M19),Budget!M19) -> 17000 | N19: =IF(12<=$R$2,N(Actuals!N19),Budget!N19) -> 17000 | O19: =SUM(C19:N19) -> 207000 | P19: =Budget!O19 -> 204000 | Q19: =O19-P19 -> 3000 | R19: =IF(P19=0,"",Q19/ABS(P19)) -> 0.014705882
B20: Profit before tax | C20: =IF(COUNT(C6:C7,C9,C11:C15)=0,"",C17-C18-C19) -> 422000 | D20: =IF(COUNT(D6:D7,D9,D11:D15)=0,"",D17-D18-D19) -> 463000 | E20: =IF(COUNT(E6:E7,E9,E11:E15)=0,"",E17-E18-E19) -> 483500 | F20: =IF(COUNT(F6:F7,F9,F11:F15)=0,"",F17-F18-F19) -> 520500 | G20: =IF(COUNT(G6:G7,G9,G11:G15)=0,"",G17-G18-G19) -> 536000 | H20: =IF(COUNT(H6:H7,H9,H11:H15)=0,"",H17-H18-H19) -> 564000 | I20: =IF(COUNT(I6:I7,I9,I11:I15)=0,"",I17-I18-I19) -> 562758.64 | J20: =IF(COUNT(J6:J7,J9,J11:J15)=0,"",J17-J18-J19) -> 569153.4 | ... N20: =IF(COUNT(N6:N7,N9,N11:N15)=0,"",N17-N18-N19) -> 703925.28 | O20: =SUM(C20:N20) -> 6744480.1 | P20: =Budget!O20 -> 6788768 | Q20: =O20-P20 -> -44287.905 | R20: =IF(P20=0,"",Q20/ABS(P20)) -> -0.0065237028
B21: Tax expense | C21: =IF(1<=$R$2,N(Actuals!C21),Budget!C21) -> 105500 | D21: =IF(2<=$R$2,N(Actuals!D21),Budget!D21) -> 115800 | E21: =IF(3<=$R$2,N(Actuals!E21),Budget!E21) -> 120900 | F21: =IF(4<=$R$2,N(Actuals!F21),Budget!F21) -> 130100 | G21: =IF(5<=$R$2,N(Actuals!G21),Budget!G21) -> 134000 | H21: =IF(6<=$R$2,N(Actuals!H21),Budget!H21) -> 141000 | I21: =IF(7<=$R$2,N(Actuals!I21),Budget!I21) -> 140689.66 | J21: =IF(8<=$R$2,N(Actuals!J21),Budget!J21) -> 142288.35 | K21: =IF(9<=$R$2,N(Actuals!K21),Budget!K21) -> 152278 | L21: =IF(10<=$R$2,N(Actuals!L21),Budget!L21) -> 162567.34 | M21: =IF(11<=$R$2,N(Actuals!M21),Budget!M21) -> 165065.36 | N21: =IF(12<=$R$2,N(Actuals!N21),Budget!N21) -> 175981.32 | O21: =SUM(C21:N21) -> 1686170 | P21: =Budget!O21 -> 1697192 | Q21: =O21-P21 -> -11021.976 | R21: =IF(P21=0,"",Q21/ABS(P21)) -> -0.0064942423
B22: Net profit | C22: =IF(COUNT(C6:C7,C9,C11:C15)=0,"",C20-C21) -> 316500 | D22: =IF(COUNT(D6:D7,D9,D11:D15)=0,"",D20-D21) -> 347200 | E22: =IF(COUNT(E6:E7,E9,E11:E15)=0,"",E20-E21) -> 362600 | F22: =IF(COUNT(F6:F7,F9,F11:F15)=0,"",F20-F21) -> 390400 | G22: =IF(COUNT(G6:G7,G9,G11:G15)=0,"",G20-G21) -> 402000 | H22: =IF(COUNT(H6:H7,H9,H11:H15)=0,"",H20-H21) -> 423000 | I22: =IF(COUNT(I6:I7,I9,I11:I15)=0,"",I20-I21) -> 422068.98 | J22: =IF(COUNT(J6:J7,J9,J11:J15)=0,"",J20-J21) -> 426865.05 | ... N22: =IF(COUNT(N6:N7,N9,N11:N15)=0,"",N20-N21) -> 527943.96 | O22: =SUM(C22:N22) -> 5058310.1 | P22: =Budget!O22 -> 5091576 | Q22: =O22-P22 -> -33265.929 | R22: =IF(P22=0,"",Q22/ABS(P22)) -> -0.0065335229
