Workbook

Sheet How to use
B2: MyFinMantra — Fixed Asset Register & Depreciation
B3: Client service format · Clear books. Confident business.
B5: Purpose | C5: A fixed asset register with depreciation under the Companies Act, 2013 (Schedule II, straight-line or written-down value, pro-rata by days) and a block-wise Income-tax depreciation schedule (half rate for assets used under 180 days), linked to the same asset list.
B7: Colour legend
B8: 12,500 | C8: Blue text on yellow = input. Type or paste your client's figures here.
B9: Formula | C9: Black text = formula. Don't overwrite; it updates automatically.
B10: Header | C10: Section and column headings.
B12: Steps
B13: Step 1 | C13: On 'Settings', set the company name and the financial year start and end dates.
B14: Step 2 | C14: On 'Asset Register', add each asset: class, purchase and put-to-use dates, cost, method and Income-tax block. Useful life fills in from Schedule II (you can override it).
B15: Step 3 | C15: For assets bought in earlier years, enter accumulated depreciation up to the start of the year (from last year's register).
B16: Step 4 | C16: For assets sold or scrapped this year, enter the disposal date and sale value; the profit or loss on sale calculates.
B17: Step 5 | C17: On 'IT Depreciation', enter each block's opening WDV. Additions and sales flow from the register automatically.
B19: Notes
C20: Companies Act: residual value 5% of cost by default; WDV rate = 1 − (residual ÷ cost)^(1 ÷ useful life). Depreciation is pro-rata for days used in the year and stops at residual value.
C21: Income-tax: 180-day test on the put-to-use date; additional depreciation, section 115BAA restrictions and block-specific rules are not modelled — adjust manually if they apply.
C22: Useful lives and rates are as commonly applied under Schedule II and the Income-tax rules; verify for your asset class.
B24: Sample figures are filled in so you can see how the format works. Replace them with your own data.
B26: Free template by MyFinMantra
B27: Accounting, GST, payroll and Virtual CFO services · www.myfinmantra.com · WhatsApp +91 97118 99555
B28: General template for guidance only — verify rates and rules for your case. Not professional advice.

Sheet Asset Register
B2: Fixed asset register — Companies Act depreciation
B3: =Settings!$C$5&" · FY "&TEXT(Settings!$C$6,"dd-mmm-yy")&" to "&TEXT(Settings!$C$7,"dd-mmm-yy") -> Sample Industries Pvt Ltd · FY 01-Apr-26 to 31-Mar-27
B5: Asset ID | C5: Description | D5: Asset class (Schedule II) | E5: Location | F5: Purchase date | G5: Put-to-use date | H5: Cost (₹) | I5: Residual % | J5: Useful life (yrs) | K5: Life override | L5: Method | M5: IT block | N5: Acc. dep. at FY start (₹) | O5: Disposal date | P5: Sale value (₹) | Q5: Opening gross | R5: Additions | S5: Opening NBV | T5: Days used in FY | U5: WDV rate | V5: Depreciation for FY | W5: Gross on disposal | X5: Acc. dep. on disposal | Y5: Closing gross | Z5: Closing acc. dep. | AA5: Closing NBV | AB5: Profit / (loss) on sale | AC5: IT: used < 180 days?
B6: FA-001 | C6: Office laptop — Dell | D6: Computers — end-user devices (desktops, laptops) | E6: Gurugram | F6: 45453 | G6: 45455 | H6: 85000 | J6: =IF(B6="","",IF(K6<>"",K6,IFERROR(INDEX(Settings!$C$14:$C$31,MATCH(D6,Settings!$B$14:$B$31,0)),""))) -> 3 | L6: SLM | M6: Computers & software | N6: 48524 | Q6: =IF(B6="","",IF(G6<Settings!$C$6,H6,0)) -> 85000 | R6: =IF(B6="","",IF(AND(G6>=Settings!$C$6,G6<=Settings!$C$7),H6,0)) -> 0 | S6: =IF(B6="","",Q6-N(N6)) -> 36476 | T6: =IF(B6="","",MAX(0,MIN(Settings!$C$7,IF(AND(O6<>"",O6<=Settings!$C$7),O6-1,Settings!$C$7))-MAX(Settings!$C$6,G6)+1)) -> 365 | U6: =IF(OR(B6="",J6=""),"",1-(IF(I6="",Settings!$C$8,I6))^(1/J6)) -> 0.63159685 | V6: =IF(OR(B6="",J6=""),"",ROUND(MAX(0,MIN(IF(L6="WDV",(S6+R6)*U6,H6*(1-IF(I6="",Settings!$C$8,I6))/J6)*T6/Settings!$C$9,(S6+R6)-H6*IF(I6="",Settings!$C$8,I6))),0)) -> 26917 | W6: =IF(B6="","",IF(AND(O6<>"",O6>=Settings!$C$6,O6<=Settings!$C$7),H6,0)) -> 0 | X6: =IF(B6="","",IF(W6>0,N(N6)+V6,0)) -> 0 | Y6: =IF(B6="","",Q6+R6-W6) -> 85000 | Z6: =IF(B6="","",N(N6)+N(V6)-X6) -> 75441 | AA6: =IF(B6="","",Y6-Z6) -> 9559 | AB6: =IF(B6="","",IF(W6>0,N(P6)-(W6-X6),0)) -> 0 | AC6: =IF(B6="","",IF(AND(R6>0,Settings!$C$7-G6+1<180),"Yes","No")) -> No
B7: FA-002 | C7: Office furniture | D7: Furniture & fittings | E7: Gurugram | F7: 45767 | G7: 45772 | H7: 240000 | J7: =IF(B7="","",IF(K7<>"",K7,IFERROR(INDEX(Settings!$C$14:$C$31,MATCH(D7,Settings!$B$14:$B$31,0)),""))) -> 10 | L7: WDV | M7: Furniture & fittings | N7: 58050 | Q7: =IF(B7="","",IF(G7<Settings!$C$6,H7,0)) -> 240000 | R7: =IF(B7="","",IF(AND(G7>=Settings!$C$6,G7<=Settings!$C$7),H7,0)) -> 0 | S7: =IF(B7="","",Q7-N(N7)) -> 181950 | T7: =IF(B7="","",MAX(0,MIN(Settings!$C$7,IF(AND(O7<>"",O7<=Settings!$C$7),O7-1,Settings!$C$7))-MAX(Settings!$C$6,G7)+1)) -> 365 | U7: =IF(OR(B7="",J7=""),"",1-(IF(I7="",Settings!$C$8,I7))^(1/J7)) -> 0.25886555 | V7: =IF(OR(B7="",J7=""),"",ROUND(MAX(0,MIN(IF(L7="WDV",(S7+R7)*U7,H7*(1-IF(I7="",Settings!$C$8,I7))/J7)*T7/Settings!$C$9,(S7+R7)-H7*IF(I7="",Settings!$C$8,I7))),0)) -> 47101 | W7: =IF(B7="","",IF(AND(O7<>"",O7>=Settings!$C$6,O7<=Settings!$C$7),H7,0)) -> 0 | X7: =IF(B7="","",IF(W7>0,N(N7)+V7,0)) -> 0 | Y7: =IF(B7="","",Q7+R7-W7) -> 240000 | Z7: =IF(B7="","",N(N7)+N(V7)-X7) -> 105151 | AA7: =IF(B7="","",Y7-Z7) -> 134849 | AB7: =IF(B7="","",IF(W7>0,N(P7)-(W7-X7),0)) -> 0 | AC7: =IF(B7="","",IF(AND(R7>0,Settings!$C$7-G7+1<180),"Yes","No")) -> No
B8: FA-003 | C8: Server rack | D8: Computers — servers & networks | E8: Gurugram | F8: 46204 | G8: 46218 | H8: 320000 | J8: =IF(B8="","",IF(K8<>"",K8,IFERROR(INDEX(Settings!$C$14:$C$31,MATCH(D8,Settings!$B$14:$B$31,0)),""))) -> 6 | L8: SLM | M8: Computers & software | N8: 0 | Q8: =IF(B8="","",IF(G8<Settings!$C$6,H8,0)) -> 0 | R8: =IF(B8="","",IF(AND(G8>=Settings!$C$6,G8<=Settings!$C$7),H8,0)) -> 320000 | S8: =IF(B8="","",Q8-N(N8)) -> 0 | T8: =IF(B8="","",MAX(0,MIN(Settings!$C$7,IF(AND(O8<>"",O8<=Settings!$C$7),O8-1,Settings!$C$7))-MAX(Settings!$C$6,G8)+1)) -> 260 | U8: =IF(OR(B8="",J8=""),"",1-(IF(I8="",Settings!$C$8,I8))^(1/J8)) -> 0.39303777 | V8: =IF(OR(B8="",J8=""),"",ROUND(MAX(0,MIN(IF(L8="WDV",(S8+R8)*U8,H8*(1-IF(I8="",Settings!$C$8,I8))/J8)*T8/Settings!$C$9,(S8+R8)-H8*IF(I8="",Settings!$C$8,I8))),0)) -> 36091 | W8: =IF(B8="","",IF(AND(O8<>"",O8>=Settings!$C$6,O8<=Settings!$C$7),H8,0)) -> 0 | X8: =IF(B8="","",IF(W8>0,N(N8)+V8,0)) -> 0 | Y8: =IF(B8="","",Q8+R8-W8) -> 320000 | Z8: =IF(B8="","",N(N8)+N(V8)-X8) -> 36091 | AA8: =IF(B8="","",Y8-Z8) -> 283909 | AB8: =IF(B8="","",IF(W8>0,N(P8)-(W8-X8),0)) -> 0 | AC8: =IF(B8="","",IF(AND(R8>0,Settings!$C$7-G8+1<180),"Yes","No")) -> No
B9: FA-004 | C9: Car — Maruti Ciaz | D9: Motor cars | E9: Gurugram | F9: 46346 | G9: 46348 | H9: 1050000 | J9: =IF(B9="","",IF(K9<>"",K9,IFERROR(INDEX(Settings!$C$14:$C$31,MATCH(D9,Settings!$B$14:$B$31,0)),""))) -> 8 | L9: WDV | M9: Motor cars (not for hire) | N9: 0 | Q9: =IF(B9="","",IF(G9<Settings!$C$6,H9,0)) -> 0 | R9: =IF(B9="","",IF(AND(G9>=Settings!$C$6,G9<=Settings!$C$7),H9,0)) -> 1050000 | S9: =IF(B9="","",Q9-N(N9)) -> 0 | T9: =IF(B9="","",MAX(0,MIN(Settings!$C$7,IF(AND(O9<>"",O9<=Settings!$C$7),O9-1,Settings!$C$7))-MAX(Settings!$C$6,G9)+1)) -> 130 | U9: =IF(OR(B9="",J9=""),"",1-(IF(I9="",Settings!$C$8,I9))^(1/J9)) -> 0.31234398 | V9: =IF(OR(B9="",J9=""),"",ROUND(MAX(0,MIN(IF(L9="WDV",(S9+R9)*U9,H9*(1-IF(I9="",Settings!$C$8,I9))/J9)*T9/Settings!$C$9,(S9+R9)-H9*IF(I9="",Settings!$C$8,I9))),0)) -> 116808 | W9: =IF(B9="","",IF(AND(O9<>"",O9>=Settings!$C$6,O9<=Settings!$C$7),H9,0)) -> 0 | X9: =IF(B9="","",IF(W9>0,N(N9)+V9,0)) -> 0 | Y9: =IF(B9="","",Q9+R9-W9) -> 1050000 | Z9: =IF(B9="","",N(N9)+N(V9)-X9) -> 116808 | AA9: =IF(B9="","",Y9-Z9) -> 933192 | AB9: =IF(B9="","",IF(W9>0,N(P9)-(W9-X9),0)) -> 0 | AC9: =IF(B9="","",IF(AND(R9>0,Settings!$C$7-G9+1<180),"Yes","No")) -> Yes
B10: FA-005 | C10: Old printer | D10: Office equipment | E10: Gurugram | F10: 44682 | G10: 44682 | H10: 45000 | J10: =IF(B10="","",IF(K10<>"",K10,IFERROR(INDEX(Settings!$C$14:$C$31,MATCH(D10,Settings!$B$14:$B$31,0)),""))) -> 5 | L10: SLM | M10: Plant & machinery — general | N10: 33500 | O10: 46295 | P10: 6000 | Q10: =IF(B10="","",IF(G10<Settings!$C$6,H10,0)) -> 45000 | R10: =IF(B10="","",IF(AND(G10>=Settings!$C$6,G10<=Settings!$C$7),H10,0)) -> 0 | S10: =IF(B10="","",Q10-N(N10)) -> 11500 | T10: =IF(B10="","",MAX(0,MIN(Settings!$C$7,IF(AND(O10<>"",O10<=Settings!$C$7),O10-1,Settings!$C$7))-MAX(Settings!$C$6,G10)+1)) -> 182 | U10: =IF(OR(B10="",J10=""),"",1-(IF(I10="",Settings!$C$8,I10))^(1/J10)) -> 0.45071973 | V10: =IF(OR(B10="",J10=""),"",ROUND(MAX(0,MIN(IF(L10="WDV",(S10+R10)*U10,H10*(1-IF(I10="",Settings!$C$8,I10))/J10)*T10/Settings!$C$9,(S10+R10)-H10*IF(I10="",Settings!$C$8,I10))),0)) -> 4263 | W10: =IF(B10="","",IF(AND(O10<>"",O10>=Settings!$C$6,O10<=Settings!$C$7),H10,0)) -> 45000 | X10: =IF(B10="","",IF(W10>0,N(N10)+V10,0)) -> 37763 | Y10: =IF(B10="","",Q10+R10-W10) -> 0 | Z10: =IF(B10="","",N(N10)+N(V10)-X10) -> 0 | AA10: =IF(B10="","",Y10-Z10) -> 0 | AB10: =IF(B10="","",IF(W10>0,N(P10)-(W10-X10),0)) -> -1237 | AC10: =IF(B10="","",IF(AND(R10>0,Settings!$C$7-G10+1<180),"Yes","No")) -> No
J11: =IF(B11="","",IF(K11<>"",K11,IFERROR(INDEX(Settings!$C$14:$C$31,MATCH(D11,Settings!$B$14:$B$31,0)),""))) | Q11: =IF(B11="","",IF(G11<Settings!$C$6,H11,0)) | R11: =IF(B11="","",IF(AND(G11>=Settings!$C$6,G11<=Settings!$C$7),H11,0)) | S11: =IF(B11="","",Q11-N(N11)) | T11: =IF(B11="","",MAX(0,MIN(Settings!$C$7,IF(AND(O11<>"",O11<=Settings!$C$7),O11-1,Settings!$C$7))-MAX(Settings!$C$6,G11)+1)) | U11: =IF(OR(B11="",J11=""),"",1-(IF(I11="",Settings!$C$8,I11))^(1/J11)) | V11: =IF(OR(B11="",J11=""),"",ROUND(MAX(0,MIN(IF(L11="WDV",(S11+R11)*U11,H11*(1-IF(I11="",Settings!$C$8,I11))/J11)*T11/Settings!$C$9,(S11+R11)-H11*IF(I11="",Settings!$C$8,I11))),0)) | W11: =IF(B11="","",IF(AND(O11<>"",O11>=Settings!$C$6,O11<=Settings!$C$7),H11,0)) | X11: =IF(B11="","",IF(W11>0,N(N11)+V11,0)) | Y11: =IF(B11="","",Q11+R11-W11) | Z11: =IF(B11="","",N(N11)+N(V11)-X11) | AA11: =IF(B11="","",Y11-Z11) | AB11: =IF(B11="","",IF(W11>0,N(P11)-(W11-X11),0)) | AC11: =IF(B11="","",IF(AND(R11>0,Settings!$C$7-G11+1<180),"Yes","No"))
J12: =IF(B12="","",IF(K12<>"",K12,IFERROR(INDEX(Settings!$C$14:$C$31,MATCH(D12,Settings!$B$14:$B$31,0)),""))) | Q12: =IF(B12="","",IF(G12<Settings!$C$6,H12,0)) | R12: =IF(B12="","",IF(AND(G12>=Settings!$C$6,G12<=Settings!$C$7),H12,0)) | S12: =IF(B12="","",Q12-N(N12)) | T12: =IF(B12="","",MAX(0,MIN(Settings!$C$7,IF(AND(O12<>"",O12<=Settings!$C$7),O12-1,Settings!$C$7))-MAX(Settings!$C$6,G12)+1)) | U12: =IF(OR(B12="",J12=""),"",1-(IF(I12="",Settings!$C$8,I12))^(1/J12)) | V12: =IF(OR(B12="",J12=""),"",ROUND(MAX(0,MIN(IF(L12="WDV",(S12+R12)*U12,H12*(1-IF(I12="",Settings!$C$8,I12))/J12)*T12/Settings!$C$9,(S12+R12)-H12*IF(I12="",Settings!$C$8,I12))),0)) | W12: =IF(B12="","",IF(AND(O12<>"",O12>=Settings!$C$6,O12<=Settings!$C$7),H12,0)) | X12: =IF(B12="","",IF(W12>0,N(N12)+V12,0)) | Y12: =IF(B12="","",Q12+R12-W12) | Z12: =IF(B12="","",N(N12)+N(V12)-X12) | AA12: =IF(B12="","",Y12-Z12) | AB12: =IF(B12="","",IF(W12>0,N(P12)-(W12-X12),0)) | AC12: =IF(B12="","",IF(AND(R12>0,Settings!$C$7-G12+1<180),"Yes","No"))
J13: =IF(B13="","",IF(K13<>"",K13,IFERROR(INDEX(Settings!$C$14:$C$31,MATCH(D13,Settings!$B$14:$B$31,0)),""))) | Q13: =IF(B13="","",IF(G13<Settings!$C$6,H13,0)) | R13: =IF(B13="","",IF(AND(G13>=Settings!$C$6,G13<=Settings!$C$7),H13,0)) | S13: =IF(B13="","",Q13-N(N13)) | T13: =IF(B13="","",MAX(0,MIN(Settings!$C$7,IF(AND(O13<>"",O13<=Settings!$C$7),O13-1,Settings!$C$7))-MAX(Settings!$C$6,G13)+1)) | U13: =IF(OR(B13="",J13=""),"",1-(IF(I13="",Settings!$C$8,I13))^(1/J13)) | V13: =IF(OR(B13="",J13=""),"",ROUND(MAX(0,MIN(IF(L13="WDV",(S13+R13)*U13,H13*(1-IF(I13="",Settings!$C$8,I13))/J13)*T13/Settings!$C$9,(S13+R13)-H13*IF(I13="",Settings!$C$8,I13))),0)) | W13: =IF(B13="","",IF(AND(O13<>"",O13>=Settings!$C$6,O13<=Settings!$C$7),H13,0)) | X13: =IF(B13="","",IF(W13>0,N(N13)+V13,0)) | Y13: =IF(B13="","",Q13+R13-W13) | Z13: =IF(B13="","",N(N13)+N(V13)-X13) | AA13: =IF(B13="","",Y13-Z13) | AB13: =IF(B13="","",IF(W13>0,N(P13)-(W13-X13),0)) | AC13: =IF(B13="","",IF(AND(R13>0,Settings!$C$7-G13+1<180),"Yes","No"))
J14: =IF(B14="","",IF(K14<>"",K14,IFERROR(INDEX(Settings!$C$14:$C$31,MATCH(D14,Settings!$B$14:$B$31,0)),""))) | Q14: =IF(B14="","",IF(G14<Settings!$C$6,H14,0)) | R14: =IF(B14="","",IF(AND(G14>=Settings!$C$6,G14<=Settings!$C$7),H14,0)) | S14: =IF(B14="","",Q14-N(N14)) | T14: =IF(B14="","",MAX(0,MIN(Settings!$C$7,IF(AND(O14<>"",O14<=Settings!$C$7),O14-1,Settings!$C$7))-MAX(Settings!$C$6,G14)+1)) | U14: =IF(OR(B14="",J14=""),"",1-(IF(I14="",Settings!$C$8,I14))^(1/J14)) | V14: =IF(OR(B14="",J14=""),"",ROUND(MAX(0,MIN(IF(L14="WDV",(S14+R14)*U14,H14*(1-IF(I14="",Settings!$C$8,I14))/J14)*T14/Settings!$C$9,(S14+R14)-H14*IF(I14="",Settings!$C$8,I14))),0)) | W14: =IF(B14="","",IF(AND(O14<>"",O14>=Settings!$C$6,O14<=Settings!$C$7),H14,0)) | X14: =IF(B14="","",IF(W14>0,N(N14)+V14,0)) | Y14: =IF(B14="","",Q14+R14-W14) | Z14: =IF(B14="","",N(N14)+N(V14)-X14) | AA14: =IF(B14="","",Y14-Z14) | AB14: =IF(B14="","",IF(W14>0,N(P14)-(W14-X14),0)) | AC14: =IF(B14="","",IF(AND(R14>0,Settings!$C$7-G14+1<180),"Yes","No"))
J15: =IF(B15="","",IF(K15<>"",K15,IFERROR(INDEX(Settings!$C$14:$C$31,MATCH(D15,Settings!$B$14:$B$31,0)),""))) | Q15: =IF(B15="","",IF(G15<Settings!$C$6,H15,0)) | R15: =IF(B15="","",IF(AND(G15>=Settings!$C$6,G15<=Settings!$C$7),H15,0)) | S15: =IF(B15="","",Q15-N(N15)) | T15: =IF(B15="","",MAX(0,MIN(Settings!$C$7,IF(AND(O15<>"",O15<=Settings!$C$7),O15-1,Settings!$C$7))-MAX(Settings!$C$6,G15)+1)) | U15: =IF(OR(B15="",J15=""),"",1-(IF(I15="",Settings!$C$8,I15))^(1/J15)) | V15: =IF(OR(B15="",J15=""),"",ROUND(MAX(0,MIN(IF(L15="WDV",(S15+R15)*U15,H15*(1-IF(I15="",Settings!$C$8,I15))/J15)*T15/Settings!$C$9,(S15+R15)-H15*IF(I15="",Settings!$C$8,I15))),0)) | W15: =IF(B15="","",IF(AND(O15<>"",O15>=Settings!$C$6,O15<=Settings!$C$7),H15,0)) | X15: =IF(B15="","",IF(W15>0,N(N15)+V15,0)) | Y15: =IF(B15="","",Q15+R15-W15) | Z15: =IF(B15="","",N(N15)+N(V15)-X15) | AA15: =IF(B15="","",Y15-Z15) | AB15: =IF(B15="","",IF(W15>0,N(P15)-(W15-X15),0)) | AC15: =IF(B15="","",IF(AND(R15>0,Settings!$C$7-G15+1<180),"Yes","No"))
J16: =IF(B16="","",IF(K16<>"",K16,IFERROR(INDEX(Settings!$C$14:$C$31,MATCH(D16,Settings!$B$14:$B$31,0)),""))) | Q16: =IF(B16="","",IF(G16<Settings!$C$6,H16,0)) | R16: =IF(B16="","",IF(AND(G16>=Settings!$C$6,G16<=Settings!$C$7),H16,0)) | S16: =IF(B16="","",Q16-N(N16)) | T16: =IF(B16="","",MAX(0,MIN(Settings!$C$7,IF(AND(O16<>"",O16<=Settings!$C$7),O16-1,Settings!$C$7))-MAX(Settings!$C$6,G16)+1)) | U16: =IF(OR(B16="",J16=""),"",1-(IF(I16="",Settings!$C$8,I16))^(1/J16)) | V16: =IF(OR(B16="",J16=""),"",ROUND(MAX(0,MIN(IF(L16="WDV",(S16+R16)*U16,H16*(1-IF(I16="",Settings!$C$8,I16))/J16)*T16/Settings!$C$9,(S16+R16)-H16*IF(I16="",Settings!$C$8,I16))),0)) | W16: =IF(B16="","",IF(AND(O16<>"",O16>=Settings!$C$6,O16<=Settings!$C$7),H16,0)) | X16: =IF(B16="","",IF(W16>0,N(N16)+V16,0)) | Y16: =IF(B16="","",Q16+R16-W16) | Z16: =IF(B16="","",N(N16)+N(V16)-X16) | AA16: =IF(B16="","",Y16-Z16) | AB16: =IF(B16="","",IF(W16>0,N(P16)-(W16-X16),0)) | AC16: =IF(B16="","",IF(AND(R16>0,Settings!$C$7-G16+1<180),"Yes","No"))
J17: =IF(B17="","",IF(K17<>"",K17,IFERROR(INDEX(Settings!$C$14:$C$31,MATCH(D17,Settings!$B$14:$B$31,0)),""))) | Q17: =IF(B17="","",IF(G17<Settings!$C$6,H17,0)) | R17: =IF(B17="","",IF(AND(G17>=Settings!$C$6,G17<=Settings!$C$7),H17,0)) | S17: =IF(B17="","",Q17-N(N17)) | T17: =IF(B17="","",MAX(0,MIN(Settings!$C$7,IF(AND(O17<>"",O17<=Settings!$C$7),O17-1,Settings!$C$7))-MAX(Settings!$C$6,G17)+1)) | U17: =IF(OR(B17="",J17=""),"",1-(IF(I17="",Settings!$C$8,I17))^(1/J17)) | V17: =IF(OR(B17="",J17=""),"",ROUND(MAX(0,MIN(IF(L17="WDV",(S17+R17)*U17,H17*(1-IF(I17="",Settings!$C$8,I17))/J17)*T17/Settings!$C$9,(S17+R17)-H17*IF(I17="",Settings!$C$8,I17))),0)) | W17: =IF(B17="","",IF(AND(O17<>"",O17>=Settings!$C$6,O17<=Settings!$C$7),H17,0)) | X17: =IF(B17="","",IF(W17>0,N(N17)+V17,0)) | Y17: =IF(B17="","",Q17+R17-W17) | Z17: =IF(B17="","",N(N17)+N(V17)-X17) | AA17: =IF(B17="","",Y17-Z17) | AB17: =IF(B17="","",IF(W17>0,N(P17)-(W17-X17),0)) | AC17: =IF(B17="","",IF(AND(R17>0,Settings!$C$7-G17+1<180),"Yes","No"))
J18: =IF(B18="","",IF(K18<>"",K18,IFERROR(INDEX(Settings!$C$14:$C$31,MATCH(D18,Settings!$B$14:$B$31,0)),""))) | Q18: =IF(B18="","",IF(G18<Settings!$C$6,H18,0)) | R18: =IF(B18="","",IF(AND(G18>=Settings!$C$6,G18<=Settings!$C$7),H18,0)) | S18: =IF(B18="","",Q18-N(N18)) | T18: =IF(B18="","",MAX(0,MIN(Settings!$C$7,IF(AND(O18<>"",O18<=Settings!$C$7),O18-1,Settings!$C$7))-MAX(Settings!$C$6,G18)+1)) | U18: =IF(OR(B18="",J18=""),"",1-(IF(I18="",Settings!$C$8,I18))^(1/J18)) | V18: =IF(OR(B18="",J18=""),"",ROUND(MAX(0,MIN(IF(L18="WDV",(S18+R18)*U18,H18*(1-IF(I18="",Settings!$C$8,I18))/J18)*T18/Settings!$C$9,(S18+R18)-H18*IF(I18="",Settings!$C$8,I18))),0)) | W18: =IF(B18="","",IF(AND(O18<>"",O18>=Settings!$C$6,O18<=Settings!$C$7),H18,0)) | X18: =IF(B18="","",IF(W18>0,N(N18)+V18,0)) | Y18: =IF(B18="","",Q18+R18-W18) | Z18: =IF(B18="","",N(N18)+N(V18)-X18) | AA18: =IF(B18="","",Y18-Z18) | AB18: =IF(B18="","",IF(W18>0,N(P18)-(W18-X18),0)) | AC18: =IF(B18="","",IF(AND(R18>0,Settings!$C$7-G18+1<180),"Yes","No"))
J19: =IF(B19="","",IF(K19<>"",K19,IFERROR(INDEX(Settings!$C$14:$C$31,MATCH(D19,Settings!$B$14:$B$31,0)),""))) | Q19: =IF(B19="","",IF(G19<Settings!$C$6,H19,0)) | R19: =IF(B19="","",IF(AND(G19>=Settings!$C$6,G19<=Settings!$C$7),H19,0)) | S19: =IF(B19="","",Q19-N(N19)) | T19: =IF(B19="","",MAX(0,MIN(Settings!$C$7,IF(AND(O19<>"",O19<=Settings!$C$7),O19-1,Settings!$C$7))-MAX(Settings!$C$6,G19)+1)) | U19: =IF(OR(B19="",J19=""),"",1-(IF(I19="",Settings!$C$8,I19))^(1/J19)) | V19: =IF(OR(B19="",J19=""),"",ROUND(MAX(0,MIN(IF(L19="WDV",(S19+R19)*U19,H19*(1-IF(I19="",Settings!$C$8,I19))/J19)*T19/Settings!$C$9,(S19+R19)-H19*IF(I19="",Settings!$C$8,I19))),0)) | W19: =IF(B19="","",IF(AND(O19<>"",O19>=Settings!$C$6,O19<=Settings!$C$7),H19,0)) | X19: =IF(B19="","",IF(W19>0,N(N19)+V19,0)) | Y19: =IF(B19="","",Q19+R19-W19) | Z19: =IF(B19="","",N(N19)+N(V19)-X19) | AA19: =IF(B19="","",Y19-Z19) | AB19: =IF(B19="","",IF(W19>0,N(P19)-(W19-X19),0)) | AC19: =IF(B19="","",IF(AND(R19>0,Settings!$C$7-G19+1<180),"Yes","No"))
J20: =IF(B20="","",IF(K20<>"",K20,IFERROR(INDEX(Settings!$C$14:$C$31,MATCH(D20,Settings!$B$14:$B$31,0)),""))) | Q20: =IF(B20="","",IF(G20<Settings!$C$6,H20,0)) | R20: =IF(B20="","",IF(AND(G20>=Settings!$C$6,G20<=Settings!$C$7),H20,0)) | S20: =IF(B20="","",Q20-N(N20)) | T20: =IF(B20="","",MAX(0,MIN(Settings!$C$7,IF(AND(O20<>"",O20<=Settings!$C$7),O20-1,Settings!$C$7))-MAX(Settings!$C$6,G20)+1)) | U20: =IF(OR(B20="",J20=""),"",1-(IF(I20="",Settings!$C$8,I20))^(1/J20)) | V20: =IF(OR(B20="",J20=""),"",ROUND(MAX(0,MIN(IF(L20="WDV",(S20+R20)*U20,H20*(1-IF(I20="",Settings!$C$8,I20))/J20)*T20/Settings!$C$9,(S20+R20)-H20*IF(I20="",Settings!$C$8,I20))),0)) | W20: =IF(B20="","",IF(AND(O20<>"",O20>=Settings!$C$6,O20<=Settings!$C$7),H20,0)) | X20: =IF(B20="","",IF(W20>0,N(N20)+V20,0)) | Y20: =IF(B20="","",Q20+R20-W20) | Z20: =IF(B20="","",N(N20)+N(V20)-X20) | AA20: =IF(B20="","",Y20-Z20) | AB20: =IF(B20="","",IF(W20>0,N(P20)-(W20-X20),0)) | AC20: =IF(B20="","",IF(AND(R20>0,Settings!$C$7-G20+1<180),"Yes","No"))
J21: =IF(B21="","",IF(K21<>"",K21,IFERROR(INDEX(Settings!$C$14:$C$31,MATCH(D21,Settings!$B$14:$B$31,0)),""))) | Q21: =IF(B21="","",IF(G21<Settings!$C$6,H21,0)) | R21: =IF(B21="","",IF(AND(G21>=Settings!$C$6,G21<=Settings!$C$7),H21,0)) | S21: =IF(B21="","",Q21-N(N21)) | T21: =IF(B21="","",MAX(0,MIN(Settings!$C$7,IF(AND(O21<>"",O21<=Settings!$C$7),O21-1,Settings!$C$7))-MAX(Settings!$C$6,G21)+1)) | U21: =IF(OR(B21="",J21=""),"",1-(IF(I21="",Settings!$C$8,I21))^(1/J21)) | V21: =IF(OR(B21="",J21=""),"",ROUND(MAX(0,MIN(IF(L21="WDV",(S21+R21)*U21,H21*(1-IF(I21="",Settings!$C$8,I21))/J21)*T21/Settings!$C$9,(S21+R21)-H21*IF(I21="",Settings!$C$8,I21))),0)) | W21: =IF(B21="","",IF(AND(O21<>"",O21>=Settings!$C$6,O21<=Settings!$C$7),H21,0)) | X21: =IF(B21="","",IF(W21>0,N(N21)+V21,0)) | Y21: =IF(B21="","",Q21+R21-W21) | Z21: =IF(B21="","",N(N21)+N(V21)-X21) | AA21: =IF(B21="","",Y21-Z21) | AB21: =IF(B21="","",IF(W21>0,N(P21)-(W21-X21),0)) | AC21: =IF(B21="","",IF(AND(R21>0,Settings!$C$7-G21+1<180),"Yes","No"))
J22: =IF(B22="","",IF(K22<>"",K22,IFERROR(INDEX(Settings!$C$14:$C$31,MATCH(D22,Settings!$B$14:$B$31,0)),""))) | Q22: =IF(B22="","",IF(G22<Settings!$C$6,H22,0)) | R22: =IF(B22="","",IF(AND(G22>=Settings!$C$6,G22<=Settings!$C$7),H22,0)) | S22: =IF(B22="","",Q22-N(N22)) | T22: =IF(B22="","",MAX(0,MIN(Settings!$C$7,IF(AND(O22<>"",O22<=Settings!$C$7),O22-1,Settings!$C$7))-MAX(Settings!$C$6,G22)+1)) | U22: =IF(OR(B22="",J22=""),"",1-(IF(I22="",Settings!$C$8,I22))^(1/J22)) | V22: =IF(OR(B22="",J22=""),"",ROUND(MAX(0,MIN(IF(L22="WDV",(S22+R22)*U22,H22*(1-IF(I22="",Settings!$C$8,I22))/J22)*T22/Settings!$C$9,(S22+R22)-H22*IF(I22="",Settings!$C$8,I22))),0)) | W22: =IF(B22="","",IF(AND(O22<>"",O22>=Settings!$C$6,O22<=Settings!$C$7),H22,0)) | X22: =IF(B22="","",IF(W22>0,N(N22)+V22,0)) | Y22: =IF(B22="","",Q22+R22-W22) | Z22: =IF(B22="","",N(N22)+N(V22)-X22) | AA22: =IF(B22="","",Y22-Z22) | AB22: =IF(B22="","",IF(W22>0,N(P22)-(W22-X22),0)) | AC22: =IF(B22="","",IF(AND(R22>0,Settings!$C$7-G22+1<180),"Yes","No"))
... J155: =IF(B155="","",IF(K155<>"",K155,IFERROR(INDEX(Settings!$C$14:$C$31,MATCH(D155,Settings!$B$14:$B$31,0)),""))) | Q155: =IF(B155="","",IF(G155<Settings!$C$6,H155,0)) | R155: =IF(B155="","",IF(AND(G155>=Settings!$C$6,G155<=Settings!$C$7),H155,0)) | S155: =IF(B155="","",Q155-N(N155)) | T155: =IF(B155="","",MAX(0,MIN(Settings!$C$7,IF(AND(O155<>"",O155<=Settings!$C$7),O155-1,Settings!$C$7))-MAX(Settings!$C$6,G155)+1)) | U155: =IF(OR(B155="",J155=""),"",1-(IF(I155="",Settings!$C$8,I155))^(1/J155)) | V155: =IF(OR(B155="",J155=""),"",ROUND(MAX(0,MIN(IF(L155="WDV",(S155+R155)*U155,H155*(1-IF(I155="",Settings!$C$8,I155))/J155)*T155/Settings!$C$9,(S155+R155)-H155*IF(I155="",Settings!$C$8,I155))),0)) | W155: =IF(B155="","",IF(AND(O155<>"",O155>=Settings!$C$6,O155<=Settings!$C$7),H155,0)) | X155: =IF(B155="","",IF(W155>0,N(N155)+V155,0)) | Y155: =IF(B155="","",Q155+R155-W155) | Z155: =IF(B155="","",N(N155)+N(V155)-X155) | AA155: =IF(B155="","",Y155-Z155) | AB155: =IF(B155="","",IF(W155>0,N(P155)-(W155-X155),0)) | AC155: =IF(B155="","",IF(AND(R155>0,Settings!$C$7-G155+1<180),"Yes","No"))
B156: Total | H156: =SUM(H6:H155) -> 1740000 | N156: =SUM(N6:N155) -> 140074 | P156: =SUM(P6:P155) -> 6000 | Q156: =SUM(Q6:Q155) -> 370000 | R156: =SUM(R6:R155) -> 1370000 | S156: =SUM(S6:S155) -> 229926 | V156: =SUM(V6:V155) -> 231180 | W156: =SUM(W6:W155) -> 45000 | X156: =SUM(X6:X155) -> 37763 | Y156: =SUM(Y6:Y155) -> 1695000 | Z156: =SUM(Z6:Z155) -> 333491 | AA156: =SUM(AA6:AA155) -> 1361509 | AB156: =SUM(AB6:AB155) -> -1237

Sheet Summary
B2: Class-wise summary (Companies Act)
B3: Ready for the PPE note in the financial statements
B5: Asset class | C5: Opening gross | D5: Additions | E5: Disposals | F5: Closing gross | G5: Opening acc. dep. | H5: Dep. for year | I5: On disposals | J5: Closing acc. dep. | K5: Closing NBV | L5: Opening NBV
B6: =IF(Settings!$B$14="","",Settings!$B$14) -> Buildings (other than factory) — RCC frame | C6: =SUMIFS('Asset Register'!$Q$6:$Q$155,'Asset Register'!$D$6:$D$155,$B6) -> 0 | D6: =SUMIFS('Asset Register'!$R$6:$R$155,'Asset Register'!$D$6:$D$155,$B6) -> 0 | E6: =SUMIFS('Asset Register'!$W$6:$W$155,'Asset Register'!$D$6:$D$155,$B6) -> 0 | F6: =C6+D6-E6 -> 0 | G6: =SUMIFS('Asset Register'!$N$6:$N$155,'Asset Register'!$D$6:$D$155,$B6,'Asset Register'!$Q$6:$Q$155,">0") -> 0 | H6: =SUMIFS('Asset Register'!$V$6:$V$155,'Asset Register'!$D$6:$D$155,$B6) -> 0 | I6: =SUMIFS('Asset Register'!$X$6:$X$155,'Asset Register'!$D$6:$D$155,$B6) -> 0 | J6: =G6+H6-I6 -> 0 | K6: =F6-J6 -> 0 | L6: =C6-G6 -> 0
B7: =IF(Settings!$B$15="","",Settings!$B$15) -> Buildings — non-RCC frame | C7: =SUMIFS('Asset Register'!$Q$6:$Q$155,'Asset Register'!$D$6:$D$155,$B7) -> 0 | D7: =SUMIFS('Asset Register'!$R$6:$R$155,'Asset Register'!$D$6:$D$155,$B7) -> 0 | E7: =SUMIFS('Asset Register'!$W$6:$W$155,'Asset Register'!$D$6:$D$155,$B7) -> 0 | F7: =C7+D7-E7 -> 0 | G7: =SUMIFS('Asset Register'!$N$6:$N$155,'Asset Register'!$D$6:$D$155,$B7,'Asset Register'!$Q$6:$Q$155,">0") -> 0 | H7: =SUMIFS('Asset Register'!$V$6:$V$155,'Asset Register'!$D$6:$D$155,$B7) -> 0 | I7: =SUMIFS('Asset Register'!$X$6:$X$155,'Asset Register'!$D$6:$D$155,$B7) -> 0 | J7: =G7+H7-I7 -> 0 | K7: =F7-J7 -> 0 | L7: =C7-G7 -> 0
B8: =IF(Settings!$B$16="","",Settings!$B$16) -> Factory buildings | C8: =SUMIFS('Asset Register'!$Q$6:$Q$155,'Asset Register'!$D$6:$D$155,$B8) -> 0 | D8: =SUMIFS('Asset Register'!$R$6:$R$155,'Asset Register'!$D$6:$D$155,$B8) -> 0 | E8: =SUMIFS('Asset Register'!$W$6:$W$155,'Asset Register'!$D$6:$D$155,$B8) -> 0 | F8: =C8+D8-E8 -> 0 | G8: =SUMIFS('Asset Register'!$N$6:$N$155,'Asset Register'!$D$6:$D$155,$B8,'Asset Register'!$Q$6:$Q$155,">0") -> 0 | H8: =SUMIFS('Asset Register'!$V$6:$V$155,'Asset Register'!$D$6:$D$155,$B8) -> 0 | I8: =SUMIFS('Asset Register'!$X$6:$X$155,'Asset Register'!$D$6:$D$155,$B8) -> 0 | J8: =G8+H8-I8 -> 0 | K8: =F8-J8 -> 0 | L8: =C8-G8 -> 0
B9: =IF(Settings!$B$17="","",Settings!$B$17) -> Plant & machinery — general | C9: =SUMIFS('Asset Register'!$Q$6:$Q$155,'Asset Register'!$D$6:$D$155,$B9) -> 0 | D9: =SUMIFS('Asset Register'!$R$6:$R$155,'Asset Register'!$D$6:$D$155,$B9) -> 0 | E9: =SUMIFS('Asset Register'!$W$6:$W$155,'Asset Register'!$D$6:$D$155,$B9) -> 0 | F9: =C9+D9-E9 -> 0 | G9: =SUMIFS('Asset Register'!$N$6:$N$155,'Asset Register'!$D$6:$D$155,$B9,'Asset Register'!$Q$6:$Q$155,">0") -> 0 | H9: =SUMIFS('Asset Register'!$V$6:$V$155,'Asset Register'!$D$6:$D$155,$B9) -> 0 | I9: =SUMIFS('Asset Register'!$X$6:$X$155,'Asset Register'!$D$6:$D$155,$B9) -> 0 | J9: =G9+H9-I9 -> 0 | K9: =F9-J9 -> 0 | L9: =C9-G9 -> 0
B10: =IF(Settings!$B$18="","",Settings!$B$18) -> Furniture & fittings | C10: =SUMIFS('Asset Register'!$Q$6:$Q$155,'Asset Register'!$D$6:$D$155,$B10) -> 240000 | D10: =SUMIFS('Asset Register'!$R$6:$R$155,'Asset Register'!$D$6:$D$155,$B10) -> 0 | E10: =SUMIFS('Asset Register'!$W$6:$W$155,'Asset Register'!$D$6:$D$155,$B10) -> 0 | F10: =C10+D10-E10 -> 240000 | G10: =SUMIFS('Asset Register'!$N$6:$N$155,'Asset Register'!$D$6:$D$155,$B10,'Asset Register'!$Q$6:$Q$155,">0") -> 58050 | H10: =SUMIFS('Asset Register'!$V$6:$V$155,'Asset Register'!$D$6:$D$155,$B10) -> 47101 | I10: =SUMIFS('Asset Register'!$X$6:$X$155,'Asset Register'!$D$6:$D$155,$B10) -> 0 | J10: =G10+H10-I10 -> 105151 | K10: =F10-J10 -> 134849 | L10: =C10-G10 -> 181950
B11: =IF(Settings!$B$19="","",Settings!$B$19) -> Office equipment | C11: =SUMIFS('Asset Register'!$Q$6:$Q$155,'Asset Register'!$D$6:$D$155,$B11) -> 45000 | D11: =SUMIFS('Asset Register'!$R$6:$R$155,'Asset Register'!$D$6:$D$155,$B11) -> 0 | E11: =SUMIFS('Asset Register'!$W$6:$W$155,'Asset Register'!$D$6:$D$155,$B11) -> 45000 | F11: =C11+D11-E11 -> 0 | G11: =SUMIFS('Asset Register'!$N$6:$N$155,'Asset Register'!$D$6:$D$155,$B11,'Asset Register'!$Q$6:$Q$155,">0") -> 33500 | H11: =SUMIFS('Asset Register'!$V$6:$V$155,'Asset Register'!$D$6:$D$155,$B11) -> 4263 | I11: =SUMIFS('Asset Register'!$X$6:$X$155,'Asset Register'!$D$6:$D$155,$B11) -> 37763 | J11: =G11+H11-I11 -> 0 | K11: =F11-J11 -> 0 | L11: =C11-G11 -> 11500
B12: =IF(Settings!$B$20="","",Settings!$B$20) -> Computers — end-user devices (desktops, laptops) | C12: =SUMIFS('Asset Register'!$Q$6:$Q$155,'Asset Register'!$D$6:$D$155,$B12) -> 85000 | D12: =SUMIFS('Asset Register'!$R$6:$R$155,'Asset Register'!$D$6:$D$155,$B12) -> 0 | E12: =SUMIFS('Asset Register'!$W$6:$W$155,'Asset Register'!$D$6:$D$155,$B12) -> 0 | F12: =C12+D12-E12 -> 85000 | G12: =SUMIFS('Asset Register'!$N$6:$N$155,'Asset Register'!$D$6:$D$155,$B12,'Asset Register'!$Q$6:$Q$155,">0") -> 48524 | H12: =SUMIFS('Asset Register'!$V$6:$V$155,'Asset Register'!$D$6:$D$155,$B12) -> 26917 | I12: =SUMIFS('Asset Register'!$X$6:$X$155,'Asset Register'!$D$6:$D$155,$B12) -> 0 | J12: =G12+H12-I12 -> 75441 | K12: =F12-J12 -> 9559 | L12: =C12-G12 -> 36476
B13: =IF(Settings!$B$21="","",Settings!$B$21) -> Computers — servers & networks | C13: =SUMIFS('Asset Register'!$Q$6:$Q$155,'Asset Register'!$D$6:$D$155,$B13) -> 0 | D13: =SUMIFS('Asset Register'!$R$6:$R$155,'Asset Register'!$D$6:$D$155,$B13) -> 320000 | E13: =SUMIFS('Asset Register'!$W$6:$W$155,'Asset Register'!$D$6:$D$155,$B13) -> 0 | F13: =C13+D13-E13 -> 320000 | G13: =SUMIFS('Asset Register'!$N$6:$N$155,'Asset Register'!$D$6:$D$155,$B13,'Asset Register'!$Q$6:$Q$155,">0") -> 0 | H13: =SUMIFS('Asset Register'!$V$6:$V$155,'Asset Register'!$D$6:$D$155,$B13) -> 36091 | I13: =SUMIFS('Asset Register'!$X$6:$X$155,'Asset Register'!$D$6:$D$155,$B13) -> 0 | J13: =G13+H13-I13 -> 36091 | K13: =F13-J13 -> 283909 | L13: =C13-G13 -> 0
B14: =IF(Settings!$B$22="","",Settings!$B$22) -> Electrical installations & equipment | C14: =SUMIFS('Asset Register'!$Q$6:$Q$155,'Asset Register'!$D$6:$D$155,$B14) -> 0 | D14: =SUMIFS('Asset Register'!$R$6:$R$155,'Asset Register'!$D$6:$D$155,$B14) -> 0 | E14: =SUMIFS('Asset Register'!$W$6:$W$155,'Asset Register'!$D$6:$D$155,$B14) -> 0 | F14: =C14+D14-E14 -> 0 | G14: =SUMIFS('Asset Register'!$N$6:$N$155,'Asset Register'!$D$6:$D$155,$B14,'Asset Register'!$Q$6:$Q$155,">0") -> 0 | H14: =SUMIFS('Asset Register'!$V$6:$V$155,'Asset Register'!$D$6:$D$155,$B14) -> 0 | I14: =SUMIFS('Asset Register'!$X$6:$X$155,'Asset Register'!$D$6:$D$155,$B14) -> 0 | J14: =G14+H14-I14 -> 0 | K14: =F14-J14 -> 0 | L14: =C14-G14 -> 0
B15: =IF(Settings!$B$23="","",Settings!$B$23) -> Motor cars | C15: =SUMIFS('Asset Register'!$Q$6:$Q$155,'Asset Register'!$D$6:$D$155,$B15) -> 0 | D15: =SUMIFS('Asset Register'!$R$6:$R$155,'Asset Register'!$D$6:$D$155,$B15) -> 1050000 | E15: =SUMIFS('Asset Register'!$W$6:$W$155,'Asset Register'!$D$6:$D$155,$B15) -> 0 | F15: =C15+D15-E15 -> 1050000 | G15: =SUMIFS('Asset Register'!$N$6:$N$155,'Asset Register'!$D$6:$D$155,$B15,'Asset Register'!$Q$6:$Q$155,">0") -> 0 | H15: =SUMIFS('Asset Register'!$V$6:$V$155,'Asset Register'!$D$6:$D$155,$B15) -> 116808 | I15: =SUMIFS('Asset Register'!$X$6:$X$155,'Asset Register'!$D$6:$D$155,$B15) -> 0 | J15: =G15+H15-I15 -> 116808 | K15: =F15-J15 -> 933192 | L15: =C15-G15 -> 0
B16: =IF(Settings!$B$24="","",Settings!$B$24) -> Motor cycles & scooters | C16: =SUMIFS('Asset Register'!$Q$6:$Q$155,'Asset Register'!$D$6:$D$155,$B16) -> 0 | D16: =SUMIFS('Asset Register'!$R$6:$R$155,'Asset Register'!$D$6:$D$155,$B16) -> 0 | E16: =SUMIFS('Asset Register'!$W$6:$W$155,'Asset Register'!$D$6:$D$155,$B16) -> 0 | F16: =C16+D16-E16 -> 0 | G16: =SUMIFS('Asset Register'!$N$6:$N$155,'Asset Register'!$D$6:$D$155,$B16,'Asset Register'!$Q$6:$Q$155,">0") -> 0 | H16: =SUMIFS('Asset Register'!$V$6:$V$155,'Asset Register'!$D$6:$D$155,$B16) -> 0 | I16: =SUMIFS('Asset Register'!$X$6:$X$155,'Asset Register'!$D$6:$D$155,$B16) -> 0 | J16: =G16+H16-I16 -> 0 | K16: =F16-J16 -> 0 | L16: =C16-G16 -> 0
B17: =IF(Settings!$B$25="","",Settings!$B$25) -> Laboratory equipment | C17: =SUMIFS('Asset Register'!$Q$6:$Q$155,'Asset Register'!$D$6:$D$155,$B17) -> 0 | D17: =SUMIFS('Asset Register'!$R$6:$R$155,'Asset Register'!$D$6:$D$155,$B17) -> 0 | E17: =SUMIFS('Asset Register'!$W$6:$W$155,'Asset Register'!$D$6:$D$155,$B17) -> 0 | F17: =C17+D17-E17 -> 0 | G17: =SUMIFS('Asset Register'!$N$6:$N$155,'Asset Register'!$D$6:$D$155,$B17,'Asset Register'!$Q$6:$Q$155,">0") -> 0 | H17: =SUMIFS('Asset Register'!$V$6:$V$155,'Asset Register'!$D$6:$D$155,$B17) -> 0 | I17: =SUMIFS('Asset Register'!$X$6:$X$155,'Asset Register'!$D$6:$D$155,$B17) -> 0 | J17: =G17+H17-I17 -> 0 | K17: =F17-J17 -> 0 | L17: =C17-G17 -> 0
B18: =IF(Settings!$B$26="","",Settings!$B$26) -> Computer software (intangible) | C18: =SUMIFS('Asset Register'!$Q$6:$Q$155,'Asset Register'!$D$6:$D$155,$B18) -> 0 | D18: =SUMIFS('Asset Register'!$R$6:$R$155,'Asset Register'!$D$6:$D$155,$B18) -> 0 | E18: =SUMIFS('Asset Register'!$W$6:$W$155,'Asset Register'!$D$6:$D$155,$B18) -> 0 | F18: =C18+D18-E18 -> 0 | G18: =SUMIFS('Asset Register'!$N$6:$N$155,'Asset Register'!$D$6:$D$155,$B18,'Asset Register'!$Q$6:$Q$155,">0") -> 0 | H18: =SUMIFS('Asset Register'!$V$6:$V$155,'Asset Register'!$D$6:$D$155,$B18) -> 0 | I18: =SUMIFS('Asset Register'!$X$6:$X$155,'Asset Register'!$D$6:$D$155,$B18) -> 0 | J18: =G18+H18-I18 -> 0 | K18: =F18-J18 -> 0 | L18: =C18-G18 -> 0
B19: =IF(Settings!$B$27="","",Settings!$B$27) | C19: =SUMIFS('Asset Register'!$Q$6:$Q$155,'Asset Register'!$D$6:$D$155,$B19) -> 0 | D19: =SUMIFS('Asset Register'!$R$6:$R$155,'Asset Register'!$D$6:$D$155,$B19) -> 0 | E19: =SUMIFS('Asset Register'!$W$6:$W$155,'Asset Register'!$D$6:$D$155,$B19) -> 0 | F19: =C19+D19-E19 -> 0 | G19: =SUMIFS('Asset Register'!$N$6:$N$155,'Asset Register'!$D$6:$D$155,$B19,'Asset Register'!$Q$6:$Q$155,">0") -> 0 | H19: =SUMIFS('Asset Register'!$V$6:$V$155,'Asset Register'!$D$6:$D$155,$B19) -> 0 | I19: =SUMIFS('Asset Register'!$X$6:$X$155,'Asset Register'!$D$6:$D$155,$B19) -> 0 | J19: =G19+H19-I19 -> 0 | K19: =F19-J19 -> 0 | L19: =C19-G19 -> 0
B20: =IF(Settings!$B$28="","",Settings!$B$28) | C20: =SUMIFS('Asset Register'!$Q$6:$Q$155,'Asset Register'!$D$6:$D$155,$B20) -> 0 | D20: =SUMIFS('Asset Register'!$R$6:$R$155,'Asset Register'!$D$6:$D$155,$B20) -> 0 | E20: =SUMIFS('Asset Register'!$W$6:$W$155,'Asset Register'!$D$6:$D$155,$B20) -> 0 | F20: =C20+D20-E20 -> 0 | G20: =SUMIFS('Asset Register'!$N$6:$N$155,'Asset Register'!$D$6:$D$155,$B20,'Asset Register'!$Q$6:$Q$155,">0") -> 0 | H20: =SUMIFS('Asset Register'!$V$6:$V$155,'Asset Register'!$D$6:$D$155,$B20) -> 0 | I20: =SUMIFS('Asset Register'!$X$6:$X$155,'Asset Register'!$D$6:$D$155,$B20) -> 0 | J20: =G20+H20-I20 -> 0 | K20: =F20-J20 -> 0 | L20: =C20-G20 -> 0
B21: =IF(Settings!$B$29="","",Settings!$B$29) | C21: =SUMIFS('Asset Register'!$Q$6:$Q$155,'Asset Register'!$D$6:$D$155,$B21) -> 0 | D21: =SUMIFS('Asset Register'!$R$6:$R$155,'Asset Register'!$D$6:$D$155,$B21) -> 0 | E21: =SUMIFS('Asset Register'!$W$6:$W$155,'Asset Register'!$D$6:$D$155,$B21) -> 0 | F21: =C21+D21-E21 -> 0 | G21: =SUMIFS('Asset Register'!$N$6:$N$155,'Asset Register'!$D$6:$D$155,$B21,'Asset Register'!$Q$6:$Q$155,">0") -> 0 | H21: =SUMIFS('Asset Register'!$V$6:$V$155,'Asset Register'!$D$6:$D$155,$B21) -> 0 | I21: =SUMIFS('Asset Register'!$X$6:$X$155,'Asset Register'!$D$6:$D$155,$B21) -> 0 | J21: =G21+H21-I21 -> 0 | K21: =F21-J21 -> 0 | L21: =C21-G21 -> 0
B22: =IF(Settings!$B$30="","",Settings!$B$30) | C22: =SUMIFS('Asset Register'!$Q$6:$Q$155,'Asset Register'!$D$6:$D$155,$B22) -> 0 | D22: =SUMIFS('Asset Register'!$R$6:$R$155,'Asset Register'!$D$6:$D$155,$B22) -> 0 | E22: =SUMIFS('Asset Register'!$W$6:$W$155,'Asset Register'!$D$6:$D$155,$B22) -> 0 | F22: =C22+D22-E22 -> 0 | G22: =SUMIFS('Asset Register'!$N$6:$N$155,'Asset Register'!$D$6:$D$155,$B22,'Asset Register'!$Q$6:$Q$155,">0") -> 0 | H22: =SUMIFS('Asset Register'!$V$6:$V$155,'Asset Register'!$D$6:$D$155,$B22) -> 0 | I22: =SUMIFS('Asset Register'!$X$6:$X$155,'Asset Register'!$D$6:$D$155,$B22) -> 0 | J22: =G22+H22-I22 -> 0 | K22: =F22-J22 -> 0 | L22: =C22-G22 -> 0
B23: =IF(Settings!$B$31="","",Settings!$B$31) | C23: =SUMIFS('Asset Register'!$Q$6:$Q$155,'Asset Register'!$D$6:$D$155,$B23) -> 0 | D23: =SUMIFS('Asset Register'!$R$6:$R$155,'Asset Register'!$D$6:$D$155,$B23) -> 0 | E23: =SUMIFS('Asset Register'!$W$6:$W$155,'Asset Register'!$D$6:$D$155,$B23) -> 0 | F23: =C23+D23-E23 -> 0 | G23: =SUMIFS('Asset Register'!$N$6:$N$155,'Asset Register'!$D$6:$D$155,$B23,'Asset Register'!$Q$6:$Q$155,">0") -> 0 | H23: =SUMIFS('Asset Register'!$V$6:$V$155,'Asset Register'!$D$6:$D$155,$B23) -> 0 | I23: =SUMIFS('Asset Register'!$X$6:$X$155,'Asset Register'!$D$6:$D$155,$B23) -> 0 | J23: =G23+H23-I23 -> 0 | K23: =F23-J23 -> 0 | L23: =C23-G23 -> 0
B24: Total | C24: =SUM(C6:C23) -> 370000 | D24: =SUM(D6:D23) -> 1370000 | E24: =SUM(E6:E23) -> 45000 | F24: =SUM(F6:F23) -> 1695000 | G24: =SUM(G6:G23) -> 140074 | H24: =SUM(H6:H23) -> 231180 | I24: =SUM(I6:I23) -> 37763 | J24: =SUM(J6:J23) -> 333491 | ... L24: =SUM(L6:L23) -> 229926
B26: Check: closing NBV agrees to register (should be 0) | C26: =K24-'Asset Register'!AA156 -> 0

Sheet IT Depreciation
B2: Income-tax depreciation — block of assets
B3: Opening WDV is an input; additions and sales flow from the register
B5: Block | C5: Rate | D5: Opening WDV | E5: Additions ≥ 180 days | F5: Additions < 180 days | G5: Sale proceeds | H5: WDV before dep. | I5: Depreciation | J5: Closing WDV
B6: =Settings!$E$14 -> Building — residential | C6: =Settings!$F$14 -> 0.05 | D6: 0 | E6: =SUMIFS('Asset Register'!$R$6:$R$155,'Asset Register'!$M$6:$M$155,$B6,'Asset Register'!$AC$6:$AC$155,"No") -> 0 | F6: =SUMIFS('Asset Register'!$R$6:$R$155,'Asset Register'!$M$6:$M$155,$B6,'Asset Register'!$AC$6:$AC$155,"Yes") -> 0 | G6: =SUMIFS('Asset Register'!$P$6:$P$155,'Asset Register'!$M$6:$M$155,$B6,'Asset Register'!$W$6:$W$155,">0") -> 0 | H6: =D6+E6+F6-G6 -> 0 | I6: =IF(H6<=0,0,ROUND(MAX(0,D6+E6-G6)*C6+MIN(F6,H6)*C6/2,0)) -> 0 | J6: =MAX(0,H6)-I6 -> 0
B7: =Settings!$E$15 -> Building — other | C7: =Settings!$F$15 -> 0.1 | D7: 0 | E7: =SUMIFS('Asset Register'!$R$6:$R$155,'Asset Register'!$M$6:$M$155,$B7,'Asset Register'!$AC$6:$AC$155,"No") -> 0 | F7: =SUMIFS('Asset Register'!$R$6:$R$155,'Asset Register'!$M$6:$M$155,$B7,'Asset Register'!$AC$6:$AC$155,"Yes") -> 0 | G7: =SUMIFS('Asset Register'!$P$6:$P$155,'Asset Register'!$M$6:$M$155,$B7,'Asset Register'!$W$6:$W$155,">0") -> 0 | H7: =D7+E7+F7-G7 -> 0 | I7: =IF(H7<=0,0,ROUND(MAX(0,D7+E7-G7)*C7+MIN(F7,H7)*C7/2,0)) -> 0 | J7: =MAX(0,H7)-I7 -> 0
B8: =Settings!$E$16 -> Furniture & fittings | C8: =Settings!$F$16 -> 0.1 | D8: 216000 | E8: =SUMIFS('Asset Register'!$R$6:$R$155,'Asset Register'!$M$6:$M$155,$B8,'Asset Register'!$AC$6:$AC$155,"No") -> 0 | F8: =SUMIFS('Asset Register'!$R$6:$R$155,'Asset Register'!$M$6:$M$155,$B8,'Asset Register'!$AC$6:$AC$155,"Yes") -> 0 | G8: =SUMIFS('Asset Register'!$P$6:$P$155,'Asset Register'!$M$6:$M$155,$B8,'Asset Register'!$W$6:$W$155,">0") -> 0 | H8: =D8+E8+F8-G8 -> 216000 | I8: =IF(H8<=0,0,ROUND(MAX(0,D8+E8-G8)*C8+MIN(F8,H8)*C8/2,0)) -> 21600 | J8: =MAX(0,H8)-I8 -> 194400
B9: =Settings!$E$17 -> Plant & machinery — general | C9: =Settings!$F$17 -> 0.15 | D9: 23490 | E9: =SUMIFS('Asset Register'!$R$6:$R$155,'Asset Register'!$M$6:$M$155,$B9,'Asset Register'!$AC$6:$AC$155,"No") -> 0 | F9: =SUMIFS('Asset Register'!$R$6:$R$155,'Asset Register'!$M$6:$M$155,$B9,'Asset Register'!$AC$6:$AC$155,"Yes") -> 0 | G9: =SUMIFS('Asset Register'!$P$6:$P$155,'Asset Register'!$M$6:$M$155,$B9,'Asset Register'!$W$6:$W$155,">0") -> 6000 | H9: =D9+E9+F9-G9 -> 17490 | I9: =IF(H9<=0,0,ROUND(MAX(0,D9+E9-G9)*C9+MIN(F9,H9)*C9/2,0)) -> 2624 | J9: =MAX(0,H9)-I9 -> 14866
B10: =Settings!$E$18 -> Motor cars (not for hire) | C10: =Settings!$F$18 -> 0.15 | D10: 0 | E10: =SUMIFS('Asset Register'!$R$6:$R$155,'Asset Register'!$M$6:$M$155,$B10,'Asset Register'!$AC$6:$AC$155,"No") -> 0 | F10: =SUMIFS('Asset Register'!$R$6:$R$155,'Asset Register'!$M$6:$M$155,$B10,'Asset Register'!$AC$6:$AC$155,"Yes") -> 1050000 | G10: =SUMIFS('Asset Register'!$P$6:$P$155,'Asset Register'!$M$6:$M$155,$B10,'Asset Register'!$W$6:$W$155,">0") -> 0 | H10: =D10+E10+F10-G10 -> 1050000 | I10: =IF(H10<=0,0,ROUND(MAX(0,D10+E10-G10)*C10+MIN(F10,H10)*C10/2,0)) -> 78750 | J10: =MAX(0,H10)-I10 -> 971250
B11: =Settings!$E$19 -> Computers & software | C11: =Settings!$F$19 -> 0.4 | D11: 30600 | E11: =SUMIFS('Asset Register'!$R$6:$R$155,'Asset Register'!$M$6:$M$155,$B11,'Asset Register'!$AC$6:$AC$155,"No") -> 320000 | F11: =SUMIFS('Asset Register'!$R$6:$R$155,'Asset Register'!$M$6:$M$155,$B11,'Asset Register'!$AC$6:$AC$155,"Yes") -> 0 | G11: =SUMIFS('Asset Register'!$P$6:$P$155,'Asset Register'!$M$6:$M$155,$B11,'Asset Register'!$W$6:$W$155,">0") -> 0 | H11: =D11+E11+F11-G11 -> 350600 | I11: =IF(H11<=0,0,ROUND(MAX(0,D11+E11-G11)*C11+MIN(F11,H11)*C11/2,0)) -> 140240 | J11: =MAX(0,H11)-I11 -> 210360
B12: =Settings!$E$20 -> Intangible assets | C12: =Settings!$F$20 -> 0.25 | D12: 0 | E12: =SUMIFS('Asset Register'!$R$6:$R$155,'Asset Register'!$M$6:$M$155,$B12,'Asset Register'!$AC$6:$AC$155,"No") -> 0 | F12: =SUMIFS('Asset Register'!$R$6:$R$155,'Asset Register'!$M$6:$M$155,$B12,'Asset Register'!$AC$6:$AC$155,"Yes") -> 0 | G12: =SUMIFS('Asset Register'!$P$6:$P$155,'Asset Register'!$M$6:$M$155,$B12,'Asset Register'!$W$6:$W$155,">0") -> 0 | H12: =D12+E12+F12-G12 -> 0 | I12: =IF(H12<=0,0,ROUND(MAX(0,D12+E12-G12)*C12+MIN(F12,H12)*C12/2,0)) -> 0 | J12: =MAX(0,H12)-I12 -> 0
B13: Total | D13: =SUM(D6:D12) -> 270090 | E13: =SUM(E6:E12) -> 320000 | F13: =SUM(F6:F12) -> 1050000 | G13: =SUM(G6:G12) -> 6000 | H13: =SUM(H6:H12) -> 1634090 | I13: =SUM(I6:I12) -> 243214 | J13: =SUM(J6:J12) -> 1390876
B15: If sale proceeds exceed the block's WDV (or the block becomes empty), short-term capital gains rules apply — review manually.

Sheet Settings
B2: Settings
B5: Company name | C5: Sample Industries Pvt Ltd
B6: Financial year start | C6: 46113
B7: Financial year end | C7: 46477
B8: Default residual value (% of cost) | C8: 0.05
B9: Days in year | C9: =C7-C6+1 -> 365
B12: Schedule II useful lives (Companies Act) | E12: Income-tax blocks
B13: Asset class | C13: Useful life (years) | E13: Block | F13: Rate
B14: Buildings (other than factory) — RCC frame | C14: 60 | E14: Building — residential | F14: 0.05
B15: Buildings — non-RCC frame | C15: 30 | E15: Building — other | F15: 0.1
B16: Factory buildings | C16: 30 | E16: Furniture & fittings | F16: 0.1
B17: Plant & machinery — general | C17: 15 | E17: Plant & machinery — general | F17: 0.15
B18: Furniture & fittings | C18: 10 | E18: Motor cars (not for hire) | F18: 0.15
B19: Office equipment | C19: 5 | E19: Computers & software | F19: 0.4
B20: Computers — end-user devices (desktops, laptops) | C20: 3 | E20: Intangible assets | F20: 0.25
B21: Computers — servers & networks | C21: 6
B22: Electrical installations & equipment | C22: 10
B23: Motor cars | C23: 8
B24: Motor cycles & scooters | C24: 10
B25: Laboratory equipment | C25: 10
B26: Computer software (intangible) | C26: 5
