Workbook

Sheet How to use
B2: MyFinMantra — Monthly MIS & Dashboard
B3: Client service format · Clear books. Confident business.
B5: Purpose | C5: A one-page monthly management report for the business owner: profit and loss for the month and year to date, key ratios, cash and statutory dues, plus a visual dashboard.
B7: Colour legend
B8: 12,500 | C8: Blue text on yellow = input. Type or paste your client's figures here.
B9: Formula | C9: Black text = formula. Don't overwrite; it updates automatically.
B10: Header | C10: Section and column headings.
B12: Steps
B13: Step 1 | C13: On 'Setup', enter the client name and choose the report month from the dropdown.
B14: Step 2 | C14: On 'P&L Data', enter each month's figures from Tally / Zoho (Profit & Loss for the month). Totals, gross profit, EBITDA and net profit calculate automatically.
B15: Step 3 | C15: On 'Balance Sheet Data', enter month-end balances: bank, receivables, payables, statutory dues and loans.
B16: Step 4 | C16: Review 'MIS Report' — month vs previous month, year to date and KPIs. Write 3 key observations in the commentary box.
B17: Step 5 | C17: Share 'MIS Report' and 'Dashboard' with the client (File → Export → PDF, or copy into an email).
B19: Notes
C20: Months run April to March (FY 2026-27). To start a new year, copy the file and change the month headings on 'P&L Data' and 'Balance Sheet Data' together.
C21: Debtor and creditor days use the current month's revenue and direct costs × 30. Months of cash cover = bank balance ÷ (direct costs + operating expenses) for the month.
B23: Sample figures are filled in so you can see how the format works. Replace them with your own data.
B25: Free template by MyFinMantra
B26: Accounting, GST, payroll and Virtual CFO services · www.myfinmantra.com · WhatsApp +91 97118 99555
B27: General template for guidance only — verify rates and rules for your case. Not professional advice.

Sheet Dashboard
B2: Dashboard
B3: =Setup!$C$5&" · "&Setup!$C$7 -> Sample Traders Pvt Ltd · Sep-26
B5: Revenue (month) | E5: EBITDA (month) | H5: Net profit (month) | K5: Cash & bank
B6: ='MIS Report'!C6 -> 2205000 | E6: ='MIS Report'!C17 -> 611000 | H6: ='MIS Report'!C22 -> 423000 | K6: ='MIS Report'!C29 -> 1610000
B9: Revenue (YTD) | E9: Net profit (YTD) | H9: EBITDA margin | K9: Debtor days
B10: ='MIS Report'!G6 -> 12150000 | E10: ='MIS Report'!G22 -> 2241700 | H10: ='MIS Report'!C26 -> 0.27709751 | K10: ='MIS Report'!C34 -> 34.285714

Sheet Setup
B2: Setup
B3: Choose the client and report month
B5: Client name | C5: Sample Traders Pvt Ltd
B6: Financial year | C6: 2026-27
B7: Report month | C7: Sep-26 | E7: ← pick from the dropdown
B8: Prepared by | C8: MyFinMantra

Sheet P&L Data
B2: Profit & Loss — monthly data
B3: Enter monthly figures in ₹ (blue cells). Bold shaded rows are formulas.
B5: Particulars (₹) | C5: Apr-26 | D5: May-26 | E5: Jun-26 | F5: Jul-26 | G5: Aug-26 | H5: Sep-26 | I5: Oct-26 | J5: Nov-26 | K5: Dec-26 | L5: Jan-27 | M5: Feb-27 | N5: Mar-27 | O5: Full year
B6: Revenue from operations | C6: 1850000 | D6: 1925000 | E6: 1990000 | F6: 2060000 | G6: 2120000 | H6: 2205000 | O6: =SUM(C6:N6) -> 12150000
B7: Other income | C7: 25000 | D7: 18000 | E7: 22000 | F7: 30000 | G7: 21000 | H7: 26000 | O7: =SUM(C7:N7) -> 142000
B8: Total income | C8: =IF(COUNT(C6:C7,C9,C11:C15)=0,"",C6+C7) -> 1875000 | D8: =IF(COUNT(D6:D7,D9,D11:D15)=0,"",D6+D7) -> 1943000 | E8: =IF(COUNT(E6:E7,E9,E11:E15)=0,"",E6+E7) -> 2012000 | F8: =IF(COUNT(F6:F7,F9,F11:F15)=0,"",F6+F7) -> 2090000 | G8: =IF(COUNT(G6:G7,G9,G11:G15)=0,"",G6+G7) -> 2141000 | H8: =IF(COUNT(H6:H7,H9,H11:H15)=0,"",H6+H7) -> 2231000 | I8: =IF(COUNT(I6:I7,I9,I11:I15)=0,"",I6+I7) | J8: =IF(COUNT(J6:J7,J9,J11:J15)=0,"",J6+J7) | ... N8: =IF(COUNT(N6:N7,N9,N11:N15)=0,"",N6+N7) | O8: =SUM(C8:N8) -> 12292000
B9: Direct costs / cost of sales | C9: 740000 | D9: 770000 | E9: 796000 | F9: 824000 | G9: 848000 | H9: 882000 | O9: =SUM(C9:N9) -> 4860000
B10: Gross profit | C10: =IF(COUNT(C6:C7,C9,C11:C15)=0,"",C6-C9) -> 1110000 | D10: =IF(COUNT(D6:D7,D9,D11:D15)=0,"",D6-D9) -> 1155000 | E10: =IF(COUNT(E6:E7,E9,E11:E15)=0,"",E6-E9) -> 1194000 | F10: =IF(COUNT(F6:F7,F9,F11:F15)=0,"",F6-F9) -> 1236000 | G10: =IF(COUNT(G6:G7,G9,G11:G15)=0,"",G6-G9) -> 1272000 | H10: =IF(COUNT(H6:H7,H9,H11:H15)=0,"",H6-H9) -> 1323000 | I10: =IF(COUNT(I6:I7,I9,I11:I15)=0,"",I6-I9) | J10: =IF(COUNT(J6:J7,J9,J11:J15)=0,"",J6-J9) | ... N10: =IF(COUNT(N6:N7,N9,N11:N15)=0,"",N6-N9) | O10: =SUM(C10:N10) -> 7290000
B11: Employee costs | C11: 420000 | D11: 420000 | E11: 435000 | F11: 435000 | G11: 450000 | H11: 450000 | O11: =SUM(C11:N11) -> 2610000
B12: Rent & utilities | C12: 85000 | D12: 85000 | E12: 85000 | F12: 85000 | G12: 85000 | H12: 85000 | O12: =SUM(C12:N12) -> 510000
B13: Professional & consultancy fees | C13: 45000 | D13: 40000 | E13: 52000 | F13: 45000 | G13: 48000 | H13: 60000 | O13: =SUM(C13:N13) -> 290000
B14: Sales & marketing | C14: 60000 | D14: 65000 | E14: 55000 | F14: 72000 | G14: 70000 | H14: 80000 | O14: =SUM(C14:N14) -> 402000
B15: Admin & other expenses | C15: 55000 | D15: 52000 | E15: 58000 | F15: 61000 | G15: 57000 | H15: 63000 | O15: =SUM(C15:N15) -> 346000
B16: Total operating expenses | C16: =IF(COUNT(C6:C7,C9,C11:C15)=0,"",SUM(C11:C15)) -> 665000 | D16: =IF(COUNT(D6:D7,D9,D11:D15)=0,"",SUM(D11:D15)) -> 662000 | E16: =IF(COUNT(E6:E7,E9,E11:E15)=0,"",SUM(E11:E15)) -> 685000 | F16: =IF(COUNT(F6:F7,F9,F11:F15)=0,"",SUM(F11:F15)) -> 698000 | G16: =IF(COUNT(G6:G7,G9,G11:G15)=0,"",SUM(G11:G15)) -> 710000 | H16: =IF(COUNT(H6:H7,H9,H11:H15)=0,"",SUM(H11:H15)) -> 738000 | I16: =IF(COUNT(I6:I7,I9,I11:I15)=0,"",SUM(I11:I15)) | J16: =IF(COUNT(J6:J7,J9,J11:J15)=0,"",SUM(J11:J15)) | ... N16: =IF(COUNT(N6:N7,N9,N11:N15)=0,"",SUM(N11:N15)) | O16: =SUM(C16:N16) -> 4158000
B17: EBITDA | C17: =IF(COUNT(C6:C7,C9,C11:C15)=0,"",C8-C9-C16) -> 470000 | D17: =IF(COUNT(D6:D7,D9,D11:D15)=0,"",D8-D9-D16) -> 511000 | E17: =IF(COUNT(E6:E7,E9,E11:E15)=0,"",E8-E9-E16) -> 531000 | F17: =IF(COUNT(F6:F7,F9,F11:F15)=0,"",F8-F9-F16) -> 568000 | G17: =IF(COUNT(G6:G7,G9,G11:G15)=0,"",G8-G9-G16) -> 583000 | H17: =IF(COUNT(H6:H7,H9,H11:H15)=0,"",H8-H9-H16) -> 611000 | I17: =IF(COUNT(I6:I7,I9,I11:I15)=0,"",I8-I9-I16) | J17: =IF(COUNT(J6:J7,J9,J11:J15)=0,"",J8-J9-J16) | ... N17: =IF(COUNT(N6:N7,N9,N11:N15)=0,"",N8-N9-N16) | O17: =SUM(C17:N17) -> 3274000
B18: Depreciation | C18: 30000 | D18: 30000 | E18: 30000 | F18: 30000 | G18: 30000 | H18: 30000 | O18: =SUM(C18:N18) -> 180000
B19: Finance costs | C19: 18000 | D19: 18000 | E19: 17500 | F19: 17500 | G19: 17000 | H19: 17000 | O19: =SUM(C19:N19) -> 105000
B20: Profit before tax | C20: =IF(COUNT(C6:C7,C9,C11:C15)=0,"",C17-C18-C19) -> 422000 | D20: =IF(COUNT(D6:D7,D9,D11:D15)=0,"",D17-D18-D19) -> 463000 | E20: =IF(COUNT(E6:E7,E9,E11:E15)=0,"",E17-E18-E19) -> 483500 | F20: =IF(COUNT(F6:F7,F9,F11:F15)=0,"",F17-F18-F19) -> 520500 | G20: =IF(COUNT(G6:G7,G9,G11:G15)=0,"",G17-G18-G19) -> 536000 | H20: =IF(COUNT(H6:H7,H9,H11:H15)=0,"",H17-H18-H19) -> 564000 | I20: =IF(COUNT(I6:I7,I9,I11:I15)=0,"",I17-I18-I19) | J20: =IF(COUNT(J6:J7,J9,J11:J15)=0,"",J17-J18-J19) | ... N20: =IF(COUNT(N6:N7,N9,N11:N15)=0,"",N17-N18-N19) | O20: =SUM(C20:N20) -> 2989000
B21: Tax expense | C21: 105500 | D21: 115800 | E21: 120900 | F21: 130100 | G21: 134000 | H21: 141000 | O21: =SUM(C21:N21) -> 747300
B22: Net profit | C22: =IF(COUNT(C6:C7,C9,C11:C15)=0,"",C20-C21) -> 316500 | D22: =IF(COUNT(D6:D7,D9,D11:D15)=0,"",D20-D21) -> 347200 | E22: =IF(COUNT(E6:E7,E9,E11:E15)=0,"",E20-E21) -> 362600 | F22: =IF(COUNT(F6:F7,F9,F11:F15)=0,"",F20-F21) -> 390400 | G22: =IF(COUNT(G6:G7,G9,G11:G15)=0,"",G20-G21) -> 402000 | H22: =IF(COUNT(H6:H7,H9,H11:H15)=0,"",H20-H21) -> 423000 | I22: =IF(COUNT(I6:I7,I9,I11:I15)=0,"",I20-I21) | J22: =IF(COUNT(J6:J7,J9,J11:J15)=0,"",J20-J21) | ... N22: =IF(COUNT(N6:N7,N9,N11:N15)=0,"",N20-N21) | O22: =SUM(C22:N22) -> 2241700

Sheet Balance Sheet Data
B2: Balance sheet — month-end balances
B3: Enter closing balances in ₹ from the trial balance
B5: Particulars (₹) | C5: Apr-26 | D5: May-26 | E5: Jun-26 | F5: Jul-26 | G5: Aug-26 | H5: Sep-26 | I5: Oct-26 | J5: Nov-26 | K5: Dec-26 | L5: Jan-27 | M5: Feb-27 | N5: Mar-27
B6: Cash & bank balances | C6: 1240000 | D6: 1385000 | E6: 1310000 | F6: 1465000 | G6: 1520000 | H6: 1610000
B7: Trade receivables | C7: 2150000 | D7: 2240000 | E7: 2380000 | F7: 2310000 | G7: 2450000 | H7: 2520000
B8: Inventory | C8: 0 | D8: 0 | E8: 0 | F8: 0 | G8: 0 | H8: 0
B9: Trade payables | C9: 640000 | D9: 610000 | E9: 700000 | F9: 680000 | G9: 720000 | H9: 735000
B10: GST payable (net) | C10: 112000 | D10: 118000 | E10: 121000 | F10: 126000 | G10: 130000 | H10: 136000
B11: TDS payable | C11: 38000 | D11: 38000 | E11: 39500 | F11: 39500 | G11: 41000 | H11: 41000
B12: Borrowings | C12: 1500000 | D12: 1460000 | E12: 1420000 | F12: 1380000 | G12: 1340000 | H12: 1300000

Sheet MIS Report
B2: Monthly MIS Report | P2: Month index | Q2: =MATCH(Setup!$C$7,'P&L Data'!$C$5:$N$5,0) -> 6
B3: ="Client: "&Setup!$C$5&" | Month: "&Setup!$C$7&" | FY "&Setup!$C$6 -> Client: Sample Traders Pvt Ltd | Month: Sep-26 | FY 2026-27
B5: Particulars (₹) | C5: This month | D5: Previous month | E5: Change | F5: Change % | G5: Year to date
B6: Revenue from operations | C6: =N(INDEX('P&L Data'!$C$6:$N$6,$Q$2)) -> 2205000 | D6: =IF($Q$2>1,N(INDEX('P&L Data'!$C$6:$N$6,$Q$2-1)),0) -> 2120000 | E6: =C6-D6 -> 85000 | F6: =IF(D6=0,"",E6/ABS(D6)) -> 0.04009434 | G6: =SUM(INDEX('P&L Data'!$C$6:$N$6,1):INDEX('P&L Data'!$C$6:$N$6,$Q$2)) -> 12150000
B7: Other income | C7: =N(INDEX('P&L Data'!$C$7:$N$7,$Q$2)) -> 26000 | D7: =IF($Q$2>1,N(INDEX('P&L Data'!$C$7:$N$7,$Q$2-1)),0) -> 21000 | E7: =C7-D7 -> 5000 | F7: =IF(D7=0,"",E7/ABS(D7)) -> 0.23809524 | G7: =SUM(INDEX('P&L Data'!$C$7:$N$7,1):INDEX('P&L Data'!$C$7:$N$7,$Q$2)) -> 142000
B8: Total income | C8: =N(INDEX('P&L Data'!$C$8:$N$8,$Q$2)) -> 2231000 | D8: =IF($Q$2>1,N(INDEX('P&L Data'!$C$8:$N$8,$Q$2-1)),0) -> 2141000 | E8: =C8-D8 -> 90000 | F8: =IF(D8=0,"",E8/ABS(D8)) -> 0.042036432 | G8: =SUM(INDEX('P&L Data'!$C$8:$N$8,1):INDEX('P&L Data'!$C$8:$N$8,$Q$2)) -> 12292000
B9: Direct costs / cost of sales | C9: =N(INDEX('P&L Data'!$C$9:$N$9,$Q$2)) -> 882000 | D9: =IF($Q$2>1,N(INDEX('P&L Data'!$C$9:$N$9,$Q$2-1)),0) -> 848000 | E9: =C9-D9 -> 34000 | F9: =IF(D9=0,"",E9/ABS(D9)) -> 0.04009434 | G9: =SUM(INDEX('P&L Data'!$C$9:$N$9,1):INDEX('P&L Data'!$C$9:$N$9,$Q$2)) -> 4860000
B10: Gross profit | C10: =N(INDEX('P&L Data'!$C$10:$N$10,$Q$2)) -> 1323000 | D10: =IF($Q$2>1,N(INDEX('P&L Data'!$C$10:$N$10,$Q$2-1)),0) -> 1272000 | E10: =C10-D10 -> 51000 | F10: =IF(D10=0,"",E10/ABS(D10)) -> 0.04009434 | G10: =SUM(INDEX('P&L Data'!$C$10:$N$10,1):INDEX('P&L Data'!$C$10:$N$10,$Q$2)) -> 7290000
B11: Employee costs | C11: =N(INDEX('P&L Data'!$C$11:$N$11,$Q$2)) -> 450000 | D11: =IF($Q$2>1,N(INDEX('P&L Data'!$C$11:$N$11,$Q$2-1)),0) -> 450000 | E11: =C11-D11 -> 0 | F11: =IF(D11=0,"",E11/ABS(D11)) -> 0 | G11: =SUM(INDEX('P&L Data'!$C$11:$N$11,1):INDEX('P&L Data'!$C$11:$N$11,$Q$2)) -> 2610000
B12: Rent & utilities | C12: =N(INDEX('P&L Data'!$C$12:$N$12,$Q$2)) -> 85000 | D12: =IF($Q$2>1,N(INDEX('P&L Data'!$C$12:$N$12,$Q$2-1)),0) -> 85000 | E12: =C12-D12 -> 0 | F12: =IF(D12=0,"",E12/ABS(D12)) -> 0 | G12: =SUM(INDEX('P&L Data'!$C$12:$N$12,1):INDEX('P&L Data'!$C$12:$N$12,$Q$2)) -> 510000
B13: Professional & consultancy fees | C13: =N(INDEX('P&L Data'!$C$13:$N$13,$Q$2)) -> 60000 | D13: =IF($Q$2>1,N(INDEX('P&L Data'!$C$13:$N$13,$Q$2-1)),0) -> 48000 | E13: =C13-D13 -> 12000 | F13: =IF(D13=0,"",E13/ABS(D13)) -> 0.25 | G13: =SUM(INDEX('P&L Data'!$C$13:$N$13,1):INDEX('P&L Data'!$C$13:$N$13,$Q$2)) -> 290000
B14: Sales & marketing | C14: =N(INDEX('P&L Data'!$C$14:$N$14,$Q$2)) -> 80000 | D14: =IF($Q$2>1,N(INDEX('P&L Data'!$C$14:$N$14,$Q$2-1)),0) -> 70000 | E14: =C14-D14 -> 10000 | F14: =IF(D14=0,"",E14/ABS(D14)) -> 0.14285714 | G14: =SUM(INDEX('P&L Data'!$C$14:$N$14,1):INDEX('P&L Data'!$C$14:$N$14,$Q$2)) -> 402000
B15: Admin & other expenses | C15: =N(INDEX('P&L Data'!$C$15:$N$15,$Q$2)) -> 63000 | D15: =IF($Q$2>1,N(INDEX('P&L Data'!$C$15:$N$15,$Q$2-1)),0) -> 57000 | E15: =C15-D15 -> 6000 | F15: =IF(D15=0,"",E15/ABS(D15)) -> 0.10526316 | G15: =SUM(INDEX('P&L Data'!$C$15:$N$15,1):INDEX('P&L Data'!$C$15:$N$15,$Q$2)) -> 346000
B16: Total operating expenses | C16: =N(INDEX('P&L Data'!$C$16:$N$16,$Q$2)) -> 738000 | D16: =IF($Q$2>1,N(INDEX('P&L Data'!$C$16:$N$16,$Q$2-1)),0) -> 710000 | E16: =C16-D16 -> 28000 | F16: =IF(D16=0,"",E16/ABS(D16)) -> 0.03943662 | G16: =SUM(INDEX('P&L Data'!$C$16:$N$16,1):INDEX('P&L Data'!$C$16:$N$16,$Q$2)) -> 4158000
B17: EBITDA | C17: =N(INDEX('P&L Data'!$C$17:$N$17,$Q$2)) -> 611000 | D17: =IF($Q$2>1,N(INDEX('P&L Data'!$C$17:$N$17,$Q$2-1)),0) -> 583000 | E17: =C17-D17 -> 28000 | F17: =IF(D17=0,"",E17/ABS(D17)) -> 0.048027444 | G17: =SUM(INDEX('P&L Data'!$C$17:$N$17,1):INDEX('P&L Data'!$C$17:$N$17,$Q$2)) -> 3274000
B18: Depreciation | C18: =N(INDEX('P&L Data'!$C$18:$N$18,$Q$2)) -> 30000 | D18: =IF($Q$2>1,N(INDEX('P&L Data'!$C$18:$N$18,$Q$2-1)),0) -> 30000 | E18: =C18-D18 -> 0 | F18: =IF(D18=0,"",E18/ABS(D18)) -> 0 | G18: =SUM(INDEX('P&L Data'!$C$18:$N$18,1):INDEX('P&L Data'!$C$18:$N$18,$Q$2)) -> 180000
B19: Finance costs | C19: =N(INDEX('P&L Data'!$C$19:$N$19,$Q$2)) -> 17000 | D19: =IF($Q$2>1,N(INDEX('P&L Data'!$C$19:$N$19,$Q$2-1)),0) -> 17000 | E19: =C19-D19 -> 0 | F19: =IF(D19=0,"",E19/ABS(D19)) -> 0 | G19: =SUM(INDEX('P&L Data'!$C$19:$N$19,1):INDEX('P&L Data'!$C$19:$N$19,$Q$2)) -> 105000
B20: Profit before tax | C20: =N(INDEX('P&L Data'!$C$20:$N$20,$Q$2)) -> 564000 | D20: =IF($Q$2>1,N(INDEX('P&L Data'!$C$20:$N$20,$Q$2-1)),0) -> 536000 | E20: =C20-D20 -> 28000 | F20: =IF(D20=0,"",E20/ABS(D20)) -> 0.052238806 | G20: =SUM(INDEX('P&L Data'!$C$20:$N$20,1):INDEX('P&L Data'!$C$20:$N$20,$Q$2)) -> 2989000
B21: Tax expense | C21: =N(INDEX('P&L Data'!$C$21:$N$21,$Q$2)) -> 141000 | D21: =IF($Q$2>1,N(INDEX('P&L Data'!$C$21:$N$21,$Q$2-1)),0) -> 134000 | E21: =C21-D21 -> 7000 | F21: =IF(D21=0,"",E21/ABS(D21)) -> 0.052238806 | G21: =SUM(INDEX('P&L Data'!$C$21:$N$21,1):INDEX('P&L Data'!$C$21:$N$21,$Q$2)) -> 747300
B22: Net profit | C22: =N(INDEX('P&L Data'!$C$22:$N$22,$Q$2)) -> 423000 | D22: =IF($Q$2>1,N(INDEX('P&L Data'!$C$22:$N$22,$Q$2-1)),0) -> 402000 | E22: =C22-D22 -> 21000 | F22: =IF(D22=0,"",E22/ABS(D22)) -> 0.052238806 | G22: =SUM(INDEX('P&L Data'!$C$22:$N$22,1):INDEX('P&L Data'!$C$22:$N$22,$Q$2)) -> 2241700
B24: Key ratios & position | C24: This month | D24: Previous month | G24: Year to date
B25: Gross margin % | C25: =IF(C6=0,"",C10/C6) -> 0.6 | D25: =IF(D6=0,"",D10/D6) -> 0.6 | G25: =IF(G6=0,"",G10/G6) -> 0.6
B26: EBITDA margin % | C26: =IF(C6=0,"",C17/C6) -> 0.27709751 | D26: =IF(D6=0,"",D17/D6) -> 0.275 | G26: =IF(G6=0,"",G17/G6) -> 0.26946502
B27: Net profit margin % | C27: =IF(C6=0,"",C22/C6) -> 0.19183673 | D27: =IF(D6=0,"",D22/D6) -> 0.18962264 | G27: =IF(G6=0,"",G22/G6) -> 0.18450206
B28: Operating expenses % of revenue | C28: =IF(C6=0,"",C16/C6) -> 0.33469388 | D28: =IF(D6=0,"",D16/D6) -> 0.33490566 | G28: =IF(G6=0,"",G16/G6) -> 0.34222222
B29: Cash & bank balance | C29: =N(INDEX('Balance Sheet Data'!$C$6:$N$6,$Q$2)) -> 1610000 | D29: =IF($Q$2>1,N(INDEX('Balance Sheet Data'!$C$6:$N$6,$Q$2-1)),0) -> 1520000
B30: Trade receivables | C30: =N(INDEX('Balance Sheet Data'!$C$7:$N$7,$Q$2)) -> 2520000 | D30: =IF($Q$2>1,N(INDEX('Balance Sheet Data'!$C$7:$N$7,$Q$2-1)),0) -> 2450000
B31: Trade payables | C31: =N(INDEX('Balance Sheet Data'!$C$9:$N$9,$Q$2)) -> 735000 | D31: =IF($Q$2>1,N(INDEX('Balance Sheet Data'!$C$9:$N$9,$Q$2-1)),0) -> 720000
B32: Statutory dues payable (GST + TDS) | C32: =N(INDEX('Balance Sheet Data'!$C$10:$N$10,$Q$2))+N(INDEX('Balance Sheet Data'!$C$11:$N$11,$Q$2)) -> 177000 | D32: =IF($Q$2>1,N(INDEX('Balance Sheet Data'!$C$10:$N$10,$Q$2-1))+N(INDEX('Balance Sheet Data'!$C$11:$N$11,$Q$2-1)),0) -> 171000
B33: Borrowings | C33: =N(INDEX('Balance Sheet Data'!$C$12:$N$12,$Q$2)) -> 1300000 | D33: =IF($Q$2>1,N(INDEX('Balance Sheet Data'!$C$12:$N$12,$Q$2-1)),0) -> 1340000
B34: Debtor days | C34: =IF(C6=0,"",C30/C6*30) -> 34.285714 | D34: =IF(D6=0,"",D30/D6*30) -> 34.669811
B35: Creditor days | C35: =IF(C9=0,"",C31/C9*30) -> 25 | D35: =IF(D9=0,"",D31/D9*30) -> 25.471698
B36: Months of expenses covered by cash | C36: =IF((C9+C16)=0,"",C29/(C9+C16)) -> 0.99382716 | D36: =IF((D9+D16)=0,"",D29/(D9+D16)) -> 0.97560976
B39: Key observations for the month
B40: Revenue up 4% over August; collections improved, debtor days stable.
B41: Marketing spend higher for the festive campaign — review ROI in October.
B42: Ensure GSTR-3B and TDS payments for September are cleared by due dates.
