Workbook

Sheet How to use
B2: MyFinMantra — Ratio Analysis (Schedule III)
B3: Client service format · Clear books. Confident business.
B5: Purpose | C5: Calculates the 11 ratios Schedule III requires companies to disclose, plus common management ratios, for two years — with the % change and a flag wherever the change exceeds 25%, which Schedule III requires you to explain.
B7: Colour legend
B8: 12,500 | C8: Blue text on yellow = input. Type or paste your client's figures here.
B9: Formula | C9: Black text = formula. Don't overwrite; it updates automatically.
B10: Header | C10: Section and column headings.
B12: Steps
B13: Step 1 | C13: On 'Inputs', enter balance sheet figures for three year-ends (needed for averages) and profit and loss figures for the current and previous year.
B14: Step 2 | C14: Open 'Ratios'. Each ratio shows its formula, both years, the change and whether an explanation is needed.
B15: Step 3 | C15: For every ratio flagged 'Explain', write the reason in the blue 'Reason for variance' column — this goes into the notes to accounts.
B17: Notes
C18: Turnover ratios use average balances (opening + closing ÷ 2).
C19: Debt Service Coverage = earnings available for debt service (PAT + depreciation + finance costs + other non-cash items) ÷ (finance costs + principal repayments).
C20: Return on investment is calculated on treasury investments: income from investments ÷ average investments. Adjust definitions to match your accounting policy and disclose them.
B22: Sample figures are filled in so you can see how the format works. Replace them with your own data.
B24: Free template by MyFinMantra
B25: Accounting, GST, payroll and Virtual CFO services · www.myfinmantra.com · WhatsApp +91 97118 99555
B26: General template for guidance only — verify rates and rules for your case. Not professional advice.

Sheet Ratios
B2: Ratio analysis
B3: Schedule III ratios and management ratios
B5: Ratio | C5: Formula | D5: FY 2025-26 | E5: FY 2026-27 | F5: Change % | G5: Explain? | H5: Reason for variance (if change > 25%)
B6: Schedule III ratios
B7: Current ratio | C7: Current assets ÷ current liabilities | D7: =IFERROR(Inputs!$D$6/Inputs!$D$9,"") -> 1.7894737 | E7: =IFERROR(Inputs!$E$6/Inputs!$E$9,"") -> 1.8247863 | F7: =IFERROR(IF(D7=0,"",(E7-D7)/ABS(D7)),"") -> 0.019733534 | G7: =IF(F7="","",IF(ABS(F7)>0.25,"Explain","—")) -> —
B8: Debt-equity ratio | C8: Total debt ÷ shareholders' equity | D8: =IFERROR(Inputs!$D$11/Inputs!$D$12,"") -> 0.67647059 | E8: =IFERROR(Inputs!$E$11/Inputs!$E$12,"") -> 0.45073375 | F8: =IFERROR(IF(D8=0,"",(E8-D8)/ABS(D8)),"") -> -0.33369793 | G8: =IF(F8="","",IF(ABS(F8)>0.25,"Explain","—")) -> Explain
B9: Debt service coverage ratio | C9: (PAT + depreciation + finance costs + non-cash) ÷ (finance costs + principal repaid) | D9: =IFERROR((Inputs!$D$22+Inputs!$D$23+Inputs!$D$24+Inputs!$D$26)/(Inputs!$D$24+Inputs!$D$27),"") -> 2.7777778 | E9: =IFERROR((Inputs!$E$22+Inputs!$E$23+Inputs!$E$24+Inputs!$E$26)/(Inputs!$E$24+Inputs!$E$27),"") -> 3.6078431 | F9: =IFERROR(IF(D9=0,"",(E9-D9)/ABS(D9)),"") -> 0.29882353 | G9: =IF(F9="","",IF(ABS(F9)>0.25,"Explain","—")) -> Explain
B10: Return on equity (ROE) | C10: (PAT − preference dividend) ÷ average shareholders' equity | D10: =IFERROR((Inputs!$D$22-Inputs!$D$29)/((Inputs!$D$12+Inputs!$C$12)/2),"") -> 0.28125 | E10: =IFERROR((Inputs!$E$22-Inputs!$E$29)/((Inputs!$E$12+Inputs!$D$12)/2),"") -> 0.29865361 | F10: =IFERROR(IF(D10=0,"",(E10-D10)/ABS(D10)),"") -> 0.061879505 | G10: =IF(F10="","",IF(ABS(F10)>0.25,"Explain","—")) -> —
B11: Inventory turnover ratio | C11: Cost of goods sold ÷ average inventory | D11: =IFERROR(Inputs!$D$20/((Inputs!$D$7+Inputs!$C$7)/2),"") -> 5.3333333 | E11: =IFERROR(Inputs!$E$20/((Inputs!$E$7+Inputs!$D$7)/2),"") -> 5.5319149 | F11: =IFERROR(IF(D11=0,"",(E11-D11)/ABS(D11)),"") -> 0.037234043 | G11: =IF(F11="","",IF(ABS(F11)>0.25,"Explain","—")) -> —
B12: Trade receivables turnover ratio | C12: Net sales ÷ average trade receivables | D12: =IFERROR(Inputs!$D$19/((Inputs!$D$8+Inputs!$C$8)/2),"") -> 6.877193 | E12: =IFERROR(Inputs!$E$19/((Inputs!$E$8+Inputs!$D$8)/2),"") -> 6.9879518 | F12: =IFERROR(IF(D12=0,"",(E12-D12)/ABS(D12)),"") -> 0.016105237 | G12: =IF(F12="","",IF(ABS(F12)>0.25,"Explain","—")) -> —
B13: Trade payables turnover ratio | C13: Purchases ÷ average trade payables | D13: =IFERROR(Inputs!$D$21/((Inputs!$D$10+Inputs!$C$10)/2),"") -> 6.627907 | E13: =IFERROR(Inputs!$E$21/((Inputs!$E$10+Inputs!$D$10)/2),"") -> 6.7171717 | F13: =IFERROR(IF(D13=0,"",(E13-D13)/ABS(D13)),"") -> 0.013468013 | G13: =IF(F13="","",IF(ABS(F13)>0.25,"Explain","—")) -> —
B14: Net capital turnover ratio | C14: Net sales ÷ working capital (current assets − current liabilities) | D14: =IFERROR(Inputs!$D$19/(Inputs!$D$6-Inputs!$D$9),"") -> 6.5333333 | E14: =IFERROR(Inputs!$E$19/(Inputs!$E$6-Inputs!$E$9),"") -> 6.0103627 | F14: =IFERROR(IF(D14=0,"",(E14-D14)/ABS(D14)),"") -> -0.080046526 | G14: =IF(F14="","",IF(ABS(F14)>0.25,"Explain","—")) -> —
B15: Net profit ratio | C15: PAT ÷ net sales | D15: =IFERROR(Inputs!$D$22/Inputs!$D$19,"") -> 0.091836735 | E15: =IFERROR(Inputs!$E$22/Inputs!$E$19,"") -> 0.10517241 | F15: =IFERROR(IF(D15=0,"",(E15-D15)/ABS(D15)),"") -> 0.14521073 | G15: =IF(F15="","",IF(ABS(F15)>0.25,"Explain","—")) -> —
B16: Return on capital employed (ROCE) | C16: EBIT ÷ capital employed (equity + total debt + deferred tax liability) | D16: =IFERROR((Inputs!$D$22+Inputs!$D$25+Inputs!$D$24)/(Inputs!$D$12+Inputs!$D$11+Inputs!$D$15),"") -> 0.25263158 | E16: =IFERROR((Inputs!$E$22+Inputs!$E$25+Inputs!$E$24)/(Inputs!$E$12+Inputs!$E$11+Inputs!$E$15),"") -> 0.26878613 | F16: =IFERROR(IF(D16=0,"",(E16-D16)/ABS(D16)),"") -> 0.063945087 | G16: =IF(F16="","",IF(ABS(F16)>0.25,"Explain","—")) -> —
B17: Return on investment | C17: Income from investments ÷ average investments | D17: =IFERROR(Inputs!$D$28/((Inputs!$D$13+Inputs!$C$13)/2),"") -> 0.062222222 | E17: =IFERROR(Inputs!$E$28/((Inputs!$E$13+Inputs!$D$13)/2),"") -> 0.058333333 | F17: =IFERROR(IF(D17=0,"",(E17-D17)/ABS(D17)),"") -> -0.0625 | G17: =IF(F17="","",IF(ABS(F17)>0.25,"Explain","—")) -> —
B18: Management ratios
B19: Quick ratio | C19: (Current assets − inventories) ÷ current liabilities | D19: =IFERROR((Inputs!$D$6-Inputs!$D$7)/Inputs!$D$9,"") -> 1.2105263 | E19: =IFERROR((Inputs!$E$6-Inputs!$E$7)/Inputs!$E$9,"") -> 1.2905983 | F19: =IFERROR(IF(D19=0,"",(E19-D19)/ABS(D19)),"") -> 0.066146414
B20: Gross profit margin | C20: (Net sales − COGS) ÷ net sales | D20: =IFERROR((Inputs!$D$19-Inputs!$D$20)/Inputs!$D$19,"") -> 0.42857143 | E20: =IFERROR((Inputs!$E$19-Inputs!$E$20)/Inputs!$E$19,"") -> 0.43965517 | F20: =IFERROR(IF(D20=0,"",(E20-D20)/ABS(D20)),"") -> 0.025862069
B21: EBITDA margin | C21: (EBIT + depreciation) ÷ net sales | D21: =IFERROR(((Inputs!$D$22+Inputs!$D$25+Inputs!$D$24)+Inputs!$D$23)/Inputs!$D$19,"") -> 0.18367347 | E21: =IFERROR(((Inputs!$E$22+Inputs!$E$25+Inputs!$E$24)+Inputs!$E$23)/Inputs!$E$19,"") -> 0.19568966 | F21: =IFERROR(IF(D21=0,"",(E21-D21)/ABS(D21)),"") -> 0.065421456
B22: Interest coverage ratio | C22: EBIT ÷ finance costs | D22: =IFERROR((Inputs!$D$22+Inputs!$D$25+Inputs!$D$24)/Inputs!$D$24,"") -> 6 | E22: =IFERROR((Inputs!$E$22+Inputs!$E$25+Inputs!$E$24)/Inputs!$E$24,"") -> 8.8571429 | F22: =IFERROR(IF(D22=0,"",(E22-D22)/ABS(D22)),"") -> 0.47619048
B23: Debtor days | C23: 365 ÷ receivables turnover | D23: =IFERROR(365/(Inputs!$D$19/((Inputs!$D$8+Inputs!$C$8)/2)),"") -> 53.07398 | E23: =IFERROR(365/(Inputs!$E$19/((Inputs!$E$8+Inputs!$D$8)/2)),"") -> 52.232759 | F23: =IFERROR(IF(D23=0,"",(E23-D23)/ABS(D23)),"") -> -0.01584997
B24: Inventory days | C24: 365 ÷ inventory turnover | D24: =IFERROR(365/(Inputs!$D$20/((Inputs!$D$7+Inputs!$C$7)/2)),"") -> 68.4375 | E24: =IFERROR(365/(Inputs!$E$20/((Inputs!$E$7+Inputs!$D$7)/2)),"") -> 65.980769 | F24: =IFERROR(IF(D24=0,"",(E24-D24)/ABS(D24)),"") -> -0.035897436
B25: Creditor days | C25: 365 ÷ payables turnover | D25: =IFERROR(365/(Inputs!$D$21/((Inputs!$D$10+Inputs!$C$10)/2)),"") -> 55.070175 | E25: =IFERROR(365/(Inputs!$E$21/((Inputs!$E$10+Inputs!$D$10)/2)),"") -> 54.338346 | F25: =IFERROR(IF(D25=0,"",(E25-D25)/ABS(D25)),"") -> -0.013289037
B26: Cash conversion cycle (days) | C26: Debtor days + inventory days − creditor days | D26: =IFERROR(D23+D24-D25,"") -> 66.441304 | E26: =IFERROR(E23+E24-E25,"") -> 63.875182 | F26: =IFERROR(IF(D26=0,"",(E26-D26)/ABS(D26)),"") -> -0.038622393
B27: Return on assets | C27: PAT ÷ average total assets | D27: =IFERROR(Inputs!$D$22/((Inputs!$D$14+Inputs!$C$14)/2),"") -> 0.12080537 | E27: =IFERROR(Inputs!$E$22/((Inputs!$E$14+Inputs!$D$14)/2),"") -> 0.14472123 | F27: =IFERROR(IF(D27=0,"",(E27-D27)/ABS(D27)),"") -> 0.19797021

Sheet Inputs
B2: Inputs
B3: ₹ — blue cells
B5: Balance sheet items | C5: 31-Mar-2025 | D5: 31-Mar-2026 | E5: 31-Mar-2027
B6: Current assets | C6: 3100000 | D6: 3400000 | E6: 4270000
B7: Inventories | C7: 1000000 | D7: 1100000 | E7: 1250000
B8: Trade receivables | C8: 1350000 | D8: 1500000 | E8: 1820000
B9: Current liabilities | C9: 1700000 | D9: 1900000 | E9: 2340000
B10: Trade payables | C10: 820000 | D10: 900000 | E10: 1080000
B11: Total debt (long-term + short-term borrowings) | C11: 2600000 | D11: 2300000 | E11: 2150000
B12: Shareholders' equity (share capital + other equity) | C12: 3000000 | D12: 3400000 | E12: 4770000
B13: Current investments + non-current investments (treasury) | C13: 400000 | D13: 500000 | E13: 700000
B14: Total assets | C14: 7300000 | D14: 7600000 | E14: 9260000
B15: Deferred tax liability | C15: 0 | D15: 0 | E15: 0
B18: Profit & loss items | D18: FY 2025-26 | E18: FY 2026-27
B19: Revenue from operations (net sales) | D19: 9800000 | E19: 11600000
B20: Cost of goods sold | D20: 5600000 | E20: 6500000
B21: Purchases | D21: 5700000 | E21: 6650000
B22: Profit after tax | D22: 900000 | E22: 1220000
B23: Depreciation and amortisation | D23: 360000 | E23: 410000
B24: Finance costs | D24: 240000 | E24: 210000
B25: Tax expense | D25: 300000 | E25: 430000
B26: Other non-cash expenses | D26: 0 | E26: 0
B27: Principal repayments of borrowings in the year | D27: 300000 | E27: 300000
B28: Income from investments | D28: 28000 | E28: 35000
B29: Preference dividend (if any) | D29: 0 | E29: 0
